package com.google.android.gm.downloadprovider;

import android.content.ContentResolver;
import android.content.ContentUris;
import android.content.ContentValues;
import android.content.Context;
import android.net.Uri;
import java.util.Locale;

public class DownloadThread extends Thread
{
  private Context mContext;
  private DownloadInfo mInfo;

  public DownloadThread(Context paramContext, DownloadInfo paramDownloadInfo)
  {
    this.mContext = paramContext;
    this.mInfo = paramDownloadInfo;
  }

  private void notifyDownloadCompleted(int paramInt1, boolean paramBoolean1, int paramInt2, int paramInt3, boolean paramBoolean2, String paramString1, String paramString2, String paramString3)
  {
    notifyThroughDatabase(paramInt1, paramBoolean1, paramInt2, paramInt3, paramBoolean2, paramString1, paramString2, paramString3);
    if (Downloads.Impl.isStatusCompleted(paramInt1))
      notifyThroughIntent();
  }

  private void notifyThroughDatabase(int paramInt1, boolean paramBoolean1, int paramInt2, int paramInt3, boolean paramBoolean2, String paramString1, String paramString2, String paramString3)
  {
    ContentValues localContentValues = new ContentValues();
    localContentValues.put("status", Integer.valueOf(paramInt1));
    localContentValues.put("_data", paramString1);
    if (paramString2 != null)
      localContentValues.put("uri", paramString2);
    localContentValues.put("mimetype", paramString3);
    localContentValues.put("lastmod", Long.valueOf(System.currentTimeMillis()));
    localContentValues.put("method", Integer.valueOf(paramInt2 + (paramInt3 << 28)));
    if (!paramBoolean1)
      localContentValues.put("numfailed", Integer.valueOf(0));
    while (true)
    {
      this.mContext.getContentResolver().update(ContentUris.withAppendedId(Downloads.Impl.CONTENT_URI, this.mInfo.mId), localContentValues, null, null);
      return;
      if (paramBoolean2)
        localContentValues.put("numfailed", Integer.valueOf(1));
      else
        localContentValues.put("numfailed", Integer.valueOf(1 + this.mInfo.mNumFailed));
    }
  }

  private void notifyThroughIntent()
  {
    Uri localUri = Uri.parse(Downloads.Impl.CONTENT_URI + "/" + this.mInfo.mId);
    this.mInfo.sendIntentIfRequested(localUri, this.mContext);
  }

  private String sanitizeMimeType(String paramString)
  {
    try
    {
      Object localObject = paramString.trim().toLowerCase(Locale.ENGLISH);
      int i = ((String)localObject).indexOf(';');
      if (i != -1)
      {
        String str = ((String)localObject).substring(0, i);
        localObject = str;
      }
      return localObject;
    }
    catch (NullPointerException localNullPointerException)
    {
    }
    return null;
  }

  private String userAgent()
  {
    String str = this.mInfo.mUserAgent;
    if ((str == null) || (str == null))
      str = "AndroidDownloadManager";
    return str;
  }

  // ERROR //
  public void run()
  {
    // Byte code:
    //   0: bipush 10
    //   2: invokestatic 190	android/os/Process:setThreadPriority	(I)V
    //   5: sipush 491
    //   8: istore_1
    //   9: aload_0
    //   10: getfield 17	com/google/android/gm/downloadprovider/DownloadThread:mInfo	Lcom/google/android/gm/downloadprovider/DownloadInfo;
    //   13: getfield 193	com/google/android/gm/downloadprovider/DownloadInfo:mRedirectCount	I
    //   16: istore_2
    //   17: aconst_null
    //   18: astore_3
    //   19: aload_0
    //   20: aload_0
    //   21: getfield 17	com/google/android/gm/downloadprovider/DownloadThread:mInfo	Lcom/google/android/gm/downloadprovider/DownloadInfo;
    //   24: getfield 196	com/google/android/gm/downloadprovider/DownloadInfo:mMimeType	Ljava/lang/String;
    //   27: invokespecial 198	com/google/android/gm/downloadprovider/DownloadThread:sanitizeMimeType	(Ljava/lang/String;)Ljava/lang/String;
    //   30: astore 4
    //   32: aconst_null
    //   33: astore 5
    //   35: aconst_null
    //   36: astore 6
    //   38: aconst_null
    //   39: astore 7
    //   41: new 108	java/lang/StringBuilder
    //   44: dup
    //   45: invokespecial 109	java/lang/StringBuilder:<init>	()V
    //   48: getstatic 85	com/google/android/gm/downloadprovider/Downloads$Impl:CONTENT_URI	Landroid/net/Uri;
    //   51: invokevirtual 113	java/lang/StringBuilder:append	(Ljava/lang/Object;)Ljava/lang/StringBuilder;
    //   54: ldc 115
    //   56: invokevirtual 118	java/lang/StringBuilder:append	(Ljava/lang/String;)Ljava/lang/StringBuilder;
    //   59: aload_0
    //   60: getfield 17	com/google/android/gm/downloadprovider/DownloadThread:mInfo	Lcom/google/android/gm/downloadprovider/DownloadInfo;
    //   63: getfield 91	com/google/android/gm/downloadprovider/DownloadInfo:mId	I
    //   66: invokevirtual 121	java/lang/StringBuilder:append	(I)Ljava/lang/StringBuilder;
    //   69: invokevirtual 125	java/lang/StringBuilder:toString	()Ljava/lang/String;
    //   72: invokestatic 131	android/net/Uri:parse	(Ljava/lang/String;)Landroid/net/Uri;
    //   75: astore 8
    //   77: sipush 4096
    //   80: newarray byte
    //   82: astore 57
    //   84: aload_0
    //   85: getfield 15	com/google/android/gm/downloadprovider/DownloadThread:mContext	Landroid/content/Context;
    //   88: ldc 200
    //   90: invokevirtual 204	android/content/Context:getSystemService	(Ljava/lang/String;)Ljava/lang/Object;
    //   93: checkcast 206	android/os/PowerManager
    //   96: iconst_1
    //   97: ldc 208
    //   99: invokevirtual 212	android/os/PowerManager:newWakeLock	(ILjava/lang/String;)Landroid/os/PowerManager$WakeLock;
    //   102: astore 7
    //   104: aload 7
    //   106: invokevirtual 217	android/os/PowerManager$WakeLock:acquire	()V
    //   109: aload_0
    //   110: getfield 17	com/google/android/gm/downloadprovider/DownloadThread:mInfo	Lcom/google/android/gm/downloadprovider/DownloadInfo;
    //   113: getfield 220	com/google/android/gm/downloadprovider/DownloadInfo:mFileName	Ljava/lang/String;
    //   116: astore_3
    //   117: iconst_0
    //   118: istore 58
    //   120: iconst_0
    //   121: istore 59
    //   123: aconst_null
    //   124: astore 60
    //   126: aconst_null
    //   127: astore 61
    //   129: aconst_null
    //   130: astore 5
    //   132: aload_3
    //   133: ifnull +181 -> 314
    //   136: aload_0
    //   137: getfield 15	com/google/android/gm/downloadprovider/DownloadThread:mContext	Landroid/content/Context;
    //   140: aload_3
    //   141: invokestatic 226	com/google/android/gm/downloadprovider/Helpers:isFilenameValid	(Landroid/content/Context;Ljava/lang/String;)Z
    //   144: ifne +98 -> 242
    //   147: sipush 492
    //   150: istore_1
    //   151: aload_0
    //   152: iload_1
    //   153: iconst_0
    //   154: iconst_0
    //   155: iconst_0
    //   156: iconst_0
    //   157: aload_3
    //   158: aconst_null
    //   159: aload_0
    //   160: getfield 17	com/google/android/gm/downloadprovider/DownloadThread:mInfo	Lcom/google/android/gm/downloadprovider/DownloadInfo;
    //   163: getfield 196	com/google/android/gm/downloadprovider/DownloadInfo:mMimeType	Ljava/lang/String;
    //   166: invokespecial 228	com/google/android/gm/downloadprovider/DownloadThread:notifyDownloadCompleted	(IZIIZLjava/lang/String;Ljava/lang/String;Ljava/lang/String;)V
    //   169: aload_0
    //   170: getfield 17	com/google/android/gm/downloadprovider/DownloadThread:mInfo	Lcom/google/android/gm/downloadprovider/DownloadInfo;
    //   173: iconst_0
    //   174: putfield 232	com/google/android/gm/downloadprovider/DownloadInfo:mHasActiveThread	Z
    //   177: aload 7
    //   179: ifnull +8 -> 187
    //   182: aload 7
    //   184: invokevirtual 235	android/os/PowerManager$WakeLock:release	()V
    //   187: iconst_0
    //   188: ifeq +7 -> 195
    //   191: aconst_null
    //   192: invokevirtual 240	android/net/http/AndroidHttpClient:close	()V
    //   195: iconst_0
    //   196: ifeq +7 -> 203
    //   199: aconst_null
    //   200: invokevirtual 243	java/io/FileOutputStream:close	()V
    //   203: aload_3
    //   204: ifnull +24 -> 228
    //   207: iload_1
    //   208: invokestatic 246	com/google/android/gm/downloadprovider/Downloads$Impl:isStatusError	(I)Z
    //   211: ifeq +4848 -> 5059
    //   214: new 248	java/io/File
    //   217: dup
    //   218: aload_3
    //   219: invokespecial 251	java/io/File:<init>	(Ljava/lang/String;)V
    //   222: invokevirtual 255	java/io/File:delete	()Z
    //   225: pop
    //   226: aconst_null
    //   227: astore_3
    //   228: aload_0
    //   229: iload_1
    //   230: iconst_0
    //   231: iconst_0
    //   232: iload_2
    //   233: iconst_0
    //   234: aload_3
    //   235: aconst_null
    //   236: aload 4
    //   238: invokespecial 228	com/google/android/gm/downloadprovider/DownloadThread:notifyDownloadCompleted	(IZIIZLjava/lang/String;Ljava/lang/String;Ljava/lang/String;)V
    //   241: return
    //   242: new 248	java/io/File
    //   245: dup
    //   246: aload_3
    //   247: invokespecial 251	java/io/File:<init>	(Ljava/lang/String;)V
    //   250: astore 73
    //   252: aload 73
    //   254: invokevirtual 258	java/io/File:exists	()Z
    //   257: istore 74
    //   259: iconst_0
    //   260: istore 58
    //   262: iconst_0
    //   263: istore 59
    //   265: aconst_null
    //   266: astore 60
    //   268: aconst_null
    //   269: astore 61
    //   271: aconst_null
    //   272: astore 6
    //   274: aconst_null
    //   275: astore 5
    //   277: iload 74
    //   279: ifeq +35 -> 314
    //   282: aload 73
    //   284: invokevirtual 261	java/io/File:length	()J
    //   287: lstore 75
    //   289: lload 75
    //   291: lconst_0
    //   292: lcmp
    //   293: istore 77
    //   295: aconst_null
    //   296: astore 6
    //   298: aconst_null
    //   299: astore 5
    //   301: iload 77
    //   303: ifne +456 -> 759
    //   306: aload 73
    //   308: invokevirtual 255	java/io/File:delete	()Z
    //   311: pop
    //   312: aconst_null
    //   313: astore_3
    //   314: iload 58
    //   316: istore 79
    //   318: lconst_0
    //   319: lstore 80
    //   321: aload_0
    //   322: invokespecial 263	com/google/android/gm/downloadprovider/DownloadThread:userAgent	()Ljava/lang/String;
    //   325: aload_0
    //   326: getfield 15	com/google/android/gm/downloadprovider/DownloadThread:mContext	Landroid/content/Context;
    //   329: invokestatic 267	android/net/http/AndroidHttpClient:newInstance	(Ljava/lang/String;Landroid/content/Context;)Landroid/net/http/AndroidHttpClient;
    //   332: astore 6
    //   334: aload 5
    //   336: ifnull +25 -> 361
    //   339: aload_0
    //   340: getfield 17	com/google/android/gm/downloadprovider/DownloadThread:mInfo	Lcom/google/android/gm/downloadprovider/DownloadInfo;
    //   343: getfield 270	com/google/android/gm/downloadprovider/DownloadInfo:mDestination	I
    //   346: istore 82
    //   348: iload 82
    //   350: ifne +11 -> 361
    //   353: aload 5
    //   355: invokevirtual 243	java/io/FileOutputStream:close	()V
    //   358: aconst_null
    //   359: astore 5
    //   361: new 272	org/apache/http/client/methods/HttpGet
    //   364: dup
    //   365: aload_0
    //   366: getfield 17	com/google/android/gm/downloadprovider/DownloadThread:mInfo	Lcom/google/android/gm/downloadprovider/DownloadInfo;
    //   369: getfield 275	com/google/android/gm/downloadprovider/DownloadInfo:mUri	Ljava/lang/String;
    //   372: invokespecial 276	org/apache/http/client/methods/HttpGet:<init>	(Ljava/lang/String;)V
    //   375: astore 83
    //   377: getstatic 281	com/google/android/gm/downloadprovider/Constants:LOGV	Z
    //   380: ifeq +35 -> 415
    //   383: ldc 208
    //   385: new 108	java/lang/StringBuilder
    //   388: dup
    //   389: invokespecial 109	java/lang/StringBuilder:<init>	()V
    //   392: ldc_w 283
    //   395: invokevirtual 118	java/lang/StringBuilder:append	(Ljava/lang/String;)Ljava/lang/StringBuilder;
    //   398: aload_0
    //   399: getfield 17	com/google/android/gm/downloadprovider/DownloadThread:mInfo	Lcom/google/android/gm/downloadprovider/DownloadInfo;
    //   402: getfield 275	com/google/android/gm/downloadprovider/DownloadInfo:mUri	Ljava/lang/String;
    //   405: invokevirtual 118	java/lang/StringBuilder:append	(Ljava/lang/String;)Ljava/lang/StringBuilder;
    //   408: invokevirtual 125	java/lang/StringBuilder:toString	()Ljava/lang/String;
    //   411: invokestatic 289	android/util/Log:v	(Ljava/lang/String;Ljava/lang/String;)I
    //   414: pop
    //   415: aload_0
    //   416: getfield 17	com/google/android/gm/downloadprovider/DownloadThread:mInfo	Lcom/google/android/gm/downloadprovider/DownloadInfo;
    //   419: getfield 292	com/google/android/gm/downloadprovider/DownloadInfo:mCookies	Ljava/lang/String;
    //   422: ifnull +18 -> 440
    //   425: aload 83
    //   427: ldc_w 294
    //   430: aload_0
    //   431: getfield 17	com/google/android/gm/downloadprovider/DownloadThread:mInfo	Lcom/google/android/gm/downloadprovider/DownloadInfo;
    //   434: getfield 292	com/google/android/gm/downloadprovider/DownloadInfo:mCookies	Ljava/lang/String;
    //   437: invokevirtual 297	org/apache/http/client/methods/HttpGet:addHeader	(Ljava/lang/String;Ljava/lang/String;)V
    //   440: aload_0
    //   441: getfield 17	com/google/android/gm/downloadprovider/DownloadThread:mInfo	Lcom/google/android/gm/downloadprovider/DownloadInfo;
    //   444: getfield 300	com/google/android/gm/downloadprovider/DownloadInfo:mReferer	Ljava/lang/String;
    //   447: ifnull +18 -> 465
    //   450: aload 83
    //   452: ldc_w 302
    //   455: aload_0
    //   456: getfield 17	com/google/android/gm/downloadprovider/DownloadThread:mInfo	Lcom/google/android/gm/downloadprovider/DownloadInfo;
    //   459: getfield 300	com/google/android/gm/downloadprovider/DownloadInfo:mReferer	Ljava/lang/String;
    //   462: invokevirtual 297	org/apache/http/client/methods/HttpGet:addHeader	(Ljava/lang/String;Ljava/lang/String;)V
    //   465: iload 59
    //   467: ifeq +53 -> 520
    //   470: aload 61
    //   472: ifnull +13 -> 485
    //   475: aload 83
    //   477: ldc_w 304
    //   480: aload 61
    //   482: invokevirtual 297	org/apache/http/client/methods/HttpGet:addHeader	(Ljava/lang/String;Ljava/lang/String;)V
    //   485: aload 83
    //   487: ldc_w 306
    //   490: new 108	java/lang/StringBuilder
    //   493: dup
    //   494: invokespecial 109	java/lang/StringBuilder:<init>	()V
    //   497: ldc_w 308
    //   500: invokevirtual 118	java/lang/StringBuilder:append	(Ljava/lang/String;)Ljava/lang/StringBuilder;
    //   503: iload 58
    //   505: invokevirtual 121	java/lang/StringBuilder:append	(I)Ljava/lang/StringBuilder;
    //   508: ldc_w 310
    //   511: invokevirtual 118	java/lang/StringBuilder:append	(Ljava/lang/String;)Ljava/lang/StringBuilder;
    //   514: invokevirtual 125	java/lang/StringBuilder:toString	()Ljava/lang/String;
    //   517: invokevirtual 297	org/apache/http/client/methods/HttpGet:addHeader	(Ljava/lang/String;Ljava/lang/String;)V
    //   520: aload 6
    //   522: aload 83
    //   524: invokevirtual 314	android/net/http/AndroidHttpClient:execute	(Lorg/apache/http/client/methods/HttpUriRequest;)Lorg/apache/http/HttpResponse;
    //   527: astore 105
    //   529: aload 105
    //   531: invokeinterface 320 1 0
    //   536: invokeinterface 326 1 0
    //   541: istore 106
    //   543: iload 106
    //   545: sipush 503
    //   548: if_icmpne +1145 -> 1693
    //   551: aload_0
    //   552: getfield 17	com/google/android/gm/downloadprovider/DownloadThread:mInfo	Lcom/google/android/gm/downloadprovider/DownloadInfo;
    //   555: getfield 106	com/google/android/gm/downloadprovider/DownloadInfo:mNumFailed	I
    //   558: iconst_5
    //   559: if_icmpge +1134 -> 1693
    //   562: getstatic 329	com/google/android/gm/downloadprovider/Constants:LOGVV	Z
    //   565: ifeq +12 -> 577
    //   568: ldc 208
    //   570: ldc_w 331
    //   573: invokestatic 289	android/util/Log:v	(Ljava/lang/String;Ljava/lang/String;)I
    //   576: pop
    //   577: sipush 193
    //   580: istore_1
    //   581: iconst_1
    //   582: istore 15
    //   584: aload 105
    //   586: ldc_w 333
    //   589: invokeinterface 337 2 0
    //   594: astore 199
    //   596: aload 199
    //   598: ifnull +5460 -> 6058
    //   601: getstatic 329	com/google/android/gm/downloadprovider/Constants:LOGVV	Z
    //   604: ifeq +35 -> 639
    //   607: ldc 208
    //   609: new 108	java/lang/StringBuilder
    //   612: dup
    //   613: invokespecial 109	java/lang/StringBuilder:<init>	()V
    //   616: ldc_w 339
    //   619: invokevirtual 118	java/lang/StringBuilder:append	(Ljava/lang/String;)Ljava/lang/StringBuilder;
    //   622: aload 199
    //   624: invokeinterface 344 1 0
    //   629: invokevirtual 118	java/lang/StringBuilder:append	(Ljava/lang/String;)Ljava/lang/StringBuilder;
    //   632: invokevirtual 125	java/lang/StringBuilder:toString	()Ljava/lang/String;
    //   635: invokestatic 289	android/util/Log:v	(Ljava/lang/String;Ljava/lang/String;)I
    //   638: pop
    //   639: aload 199
    //   641: invokeinterface 344 1 0
    //   646: invokestatic 348	java/lang/Integer:parseInt	(Ljava/lang/String;)I
    //   649: istore 204
    //   651: iload 204
    //   653: istore 14
    //   655: iload 14
    //   657: ifge +985 -> 1642
    //   660: iconst_0
    //   661: istore 14
    //   663: aload 83
    //   665: invokevirtual 351	org/apache/http/client/methods/HttpGet:abort	()V
    //   668: iconst_0
    //   669: istore 11
    //   671: aconst_null
    //   672: astore 12
    //   674: iload_2
    //   675: istore 13
    //   677: aload_0
    //   678: getfield 17	com/google/android/gm/downloadprovider/DownloadThread:mInfo	Lcom/google/android/gm/downloadprovider/DownloadInfo;
    //   681: iconst_0
    //   682: putfield 232	com/google/android/gm/downloadprovider/DownloadInfo:mHasActiveThread	Z
    //   685: aload 7
    //   687: ifnull +8 -> 695
    //   690: aload 7
    //   692: invokevirtual 235	android/os/PowerManager$WakeLock:release	()V
    //   695: aload 6
    //   697: ifnull +8 -> 705
    //   700: aload 6
    //   702: invokevirtual 240	android/net/http/AndroidHttpClient:close	()V
    //   705: aload 5
    //   707: ifnull +8 -> 715
    //   710: aload 5
    //   712: invokevirtual 243	java/io/FileOutputStream:close	()V
    //   715: aload_3
    //   716: ifnull +24 -> 740
    //   719: iload_1
    //   720: invokestatic 246	com/google/android/gm/downloadprovider/Downloads$Impl:isStatusError	(I)Z
    //   723: ifeq +4541 -> 5264
    //   726: new 248	java/io/File
    //   729: dup
    //   730: aload_3
    //   731: invokespecial 251	java/io/File:<init>	(Ljava/lang/String;)V
    //   734: invokevirtual 255	java/io/File:delete	()Z
    //   737: pop
    //   738: aconst_null
    //   739: astore_3
    //   740: aload_0
    //   741: iload_1
    //   742: iload 15
    //   744: iload 14
    //   746: iload 13
    //   748: iload 11
    //   750: aload_3
    //   751: aload 12
    //   753: aload 4
    //   755: invokespecial 228	com/google/android/gm/downloadprovider/DownloadThread:notifyDownloadCompleted	(IZIIZLjava/lang/String;Ljava/lang/String;Ljava/lang/String;)V
    //   758: return
    //   759: aload_0
    //   760: getfield 17	com/google/android/gm/downloadprovider/DownloadThread:mInfo	Lcom/google/android/gm/downloadprovider/DownloadInfo;
    //   763: getfield 354	com/google/android/gm/downloadprovider/DownloadInfo:mETag	Ljava/lang/String;
    //   766: ifnonnull +123 -> 889
    //   769: aload_0
    //   770: getfield 17	com/google/android/gm/downloadprovider/DownloadThread:mInfo	Lcom/google/android/gm/downloadprovider/DownloadInfo;
    //   773: getfield 357	com/google/android/gm/downloadprovider/DownloadInfo:mNoIntegrity	Z
    //   776: ifne +113 -> 889
    //   779: ldc 208
    //   781: ldc_w 359
    //   784: invokestatic 362	android/util/Log:d	(Ljava/lang/String;Ljava/lang/String;)I
    //   787: pop
    //   788: aload 73
    //   790: invokevirtual 255	java/io/File:delete	()Z
    //   793: pop
    //   794: sipush 412
    //   797: istore_1
    //   798: aload_0
    //   799: iload_1
    //   800: iconst_0
    //   801: iconst_0
    //   802: iconst_0
    //   803: iconst_0
    //   804: aload_3
    //   805: aconst_null
    //   806: aload_0
    //   807: getfield 17	com/google/android/gm/downloadprovider/DownloadThread:mInfo	Lcom/google/android/gm/downloadprovider/DownloadInfo;
    //   810: getfield 196	com/google/android/gm/downloadprovider/DownloadInfo:mMimeType	Ljava/lang/String;
    //   813: invokespecial 228	com/google/android/gm/downloadprovider/DownloadThread:notifyDownloadCompleted	(IZIIZLjava/lang/String;Ljava/lang/String;Ljava/lang/String;)V
    //   816: aload_0
    //   817: getfield 17	com/google/android/gm/downloadprovider/DownloadThread:mInfo	Lcom/google/android/gm/downloadprovider/DownloadInfo;
    //   820: iconst_0
    //   821: putfield 232	com/google/android/gm/downloadprovider/DownloadInfo:mHasActiveThread	Z
    //   824: aload 7
    //   826: ifnull +8 -> 834
    //   829: aload 7
    //   831: invokevirtual 235	android/os/PowerManager$WakeLock:release	()V
    //   834: iconst_0
    //   835: ifeq +7 -> 842
    //   838: aconst_null
    //   839: invokevirtual 240	android/net/http/AndroidHttpClient:close	()V
    //   842: iconst_0
    //   843: ifeq +7 -> 850
    //   846: aconst_null
    //   847: invokevirtual 243	java/io/FileOutputStream:close	()V
    //   850: aload_3
    //   851: ifnull +24 -> 875
    //   854: iload_1
    //   855: invokestatic 246	com/google/android/gm/downloadprovider/Downloads$Impl:isStatusError	(I)Z
    //   858: ifeq +4611 -> 5469
    //   861: new 248	java/io/File
    //   864: dup
    //   865: aload_3
    //   866: invokespecial 251	java/io/File:<init>	(Ljava/lang/String;)V
    //   869: invokevirtual 255	java/io/File:delete	()Z
    //   872: pop
    //   873: aconst_null
    //   874: astore_3
    //   875: aload_0
    //   876: iload_1
    //   877: iconst_0
    //   878: iconst_0
    //   879: iload_2
    //   880: iconst_0
    //   881: aload_3
    //   882: aconst_null
    //   883: aload 4
    //   885: invokespecial 228	com/google/android/gm/downloadprovider/DownloadThread:notifyDownloadCompleted	(IZIIZLjava/lang/String;Ljava/lang/String;Ljava/lang/String;)V
    //   888: return
    //   889: new 242	java/io/FileOutputStream
    //   892: dup
    //   893: aload_3
    //   894: iconst_1
    //   895: invokespecial 365	java/io/FileOutputStream:<init>	(Ljava/lang/String;Z)V
    //   898: astore 212
    //   900: lload 75
    //   902: l2i
    //   903: istore 58
    //   905: aload_0
    //   906: getfield 17	com/google/android/gm/downloadprovider/DownloadThread:mInfo	Lcom/google/android/gm/downloadprovider/DownloadInfo;
    //   909: getfield 368	com/google/android/gm/downloadprovider/DownloadInfo:mTotalBytes	I
    //   912: istore 216
    //   914: aconst_null
    //   915: astore 60
    //   917: iload 216
    //   919: iconst_m1
    //   920: if_icmpeq +15 -> 935
    //   923: aload_0
    //   924: getfield 17	com/google/android/gm/downloadprovider/DownloadThread:mInfo	Lcom/google/android/gm/downloadprovider/DownloadInfo;
    //   927: getfield 368	com/google/android/gm/downloadprovider/DownloadInfo:mTotalBytes	I
    //   930: invokestatic 371	java/lang/Integer:toString	(I)Ljava/lang/String;
    //   933: astore 60
    //   935: aload_0
    //   936: getfield 17	com/google/android/gm/downloadprovider/DownloadThread:mInfo	Lcom/google/android/gm/downloadprovider/DownloadInfo;
    //   939: getfield 354	com/google/android/gm/downloadprovider/DownloadInfo:mETag	Ljava/lang/String;
    //   942: astore 61
    //   944: iconst_1
    //   945: istore 59
    //   947: aload 212
    //   949: astore 5
    //   951: goto -637 -> 314
    //   954: astore 210
    //   956: getstatic 281	com/google/android/gm/downloadprovider/Constants:LOGV	Z
    //   959: ifeq -598 -> 361
    //   962: ldc 208
    //   964: new 108	java/lang/StringBuilder
    //   967: dup
    //   968: invokespecial 109	java/lang/StringBuilder:<init>	()V
    //   971: ldc_w 373
    //   974: invokevirtual 118	java/lang/StringBuilder:append	(Ljava/lang/String;)Ljava/lang/StringBuilder;
    //   977: aload 210
    //   979: invokevirtual 113	java/lang/StringBuilder:append	(Ljava/lang/Object;)Ljava/lang/StringBuilder;
    //   982: invokevirtual 125	java/lang/StringBuilder:toString	()Ljava/lang/String;
    //   985: invokestatic 289	android/util/Log:v	(Ljava/lang/String;Ljava/lang/String;)I
    //   988: pop
    //   989: goto -628 -> 361
    //   992: astore 43
    //   994: aload 43
    //   996: astore 44
    //   998: iconst_0
    //   999: istore 11
    //   1001: aconst_null
    //   1002: astore 12
    //   1004: iload_2
    //   1005: istore 13
    //   1007: iconst_0
    //   1008: istore 14
    //   1010: iconst_0
    //   1011: istore 15
    //   1013: ldc 208
    //   1015: new 108	java/lang/StringBuilder
    //   1018: dup
    //   1019: invokespecial 109	java/lang/StringBuilder:<init>	()V
    //   1022: ldc_w 375
    //   1025: invokevirtual 118	java/lang/StringBuilder:append	(Ljava/lang/String;)Ljava/lang/StringBuilder;
    //   1028: aload_3
    //   1029: invokevirtual 118	java/lang/StringBuilder:append	(Ljava/lang/String;)Ljava/lang/StringBuilder;
    //   1032: ldc_w 377
    //   1035: invokevirtual 118	java/lang/StringBuilder:append	(Ljava/lang/String;)Ljava/lang/StringBuilder;
    //   1038: aload 44
    //   1040: invokevirtual 113	java/lang/StringBuilder:append	(Ljava/lang/Object;)Ljava/lang/StringBuilder;
    //   1043: invokevirtual 125	java/lang/StringBuilder:toString	()Ljava/lang/String;
    //   1046: invokestatic 362	android/util/Log:d	(Ljava/lang/String;Ljava/lang/String;)I
    //   1049: pop
    //   1050: sipush 492
    //   1053: istore_1
    //   1054: aload_0
    //   1055: getfield 17	com/google/android/gm/downloadprovider/DownloadThread:mInfo	Lcom/google/android/gm/downloadprovider/DownloadInfo;
    //   1058: iconst_0
    //   1059: putfield 232	com/google/android/gm/downloadprovider/DownloadInfo:mHasActiveThread	Z
    //   1062: aload 7
    //   1064: ifnull +8 -> 1072
    //   1067: aload 7
    //   1069: invokevirtual 235	android/os/PowerManager$WakeLock:release	()V
    //   1072: aload 6
    //   1074: ifnull +8 -> 1082
    //   1077: aload 6
    //   1079: invokevirtual 240	android/net/http/AndroidHttpClient:close	()V
    //   1082: aload 5
    //   1084: ifnull +8 -> 1092
    //   1087: aload 5
    //   1089: invokevirtual 243	java/io/FileOutputStream:close	()V
    //   1092: aload_3
    //   1093: ifnull -353 -> 740
    //   1096: iload_1
    //   1097: invokestatic 246	com/google/android/gm/downloadprovider/Downloads$Impl:isStatusError	(I)Z
    //   1100: ifeq +3549 -> 4649
    //   1103: new 248	java/io/File
    //   1106: dup
    //   1107: aload_3
    //   1108: invokespecial 251	java/io/File:<init>	(Ljava/lang/String;)V
    //   1111: invokevirtual 255	java/io/File:delete	()Z
    //   1114: pop
    //   1115: aconst_null
    //   1116: astore_3
    //   1117: goto -377 -> 740
    //   1120: astore 102
    //   1122: getstatic 281	com/google/android/gm/downloadprovider/Constants:LOGV	Z
    //   1125: ifeq +73 -> 1198
    //   1128: ldc 208
    //   1130: new 108	java/lang/StringBuilder
    //   1133: dup
    //   1134: invokespecial 109	java/lang/StringBuilder:<init>	()V
    //   1137: ldc_w 379
    //   1140: invokevirtual 118	java/lang/StringBuilder:append	(Ljava/lang/String;)Ljava/lang/StringBuilder;
    //   1143: aload_0
    //   1144: getfield 17	com/google/android/gm/downloadprovider/DownloadThread:mInfo	Lcom/google/android/gm/downloadprovider/DownloadInfo;
    //   1147: getfield 275	com/google/android/gm/downloadprovider/DownloadInfo:mUri	Ljava/lang/String;
    //   1150: invokevirtual 118	java/lang/StringBuilder:append	(Ljava/lang/String;)Ljava/lang/StringBuilder;
    //   1153: ldc_w 377
    //   1156: invokevirtual 118	java/lang/StringBuilder:append	(Ljava/lang/String;)Ljava/lang/StringBuilder;
    //   1159: aload 102
    //   1161: invokevirtual 113	java/lang/StringBuilder:append	(Ljava/lang/Object;)Ljava/lang/StringBuilder;
    //   1164: invokevirtual 125	java/lang/StringBuilder:toString	()Ljava/lang/String;
    //   1167: invokestatic 362	android/util/Log:d	(Ljava/lang/String;Ljava/lang/String;)I
    //   1170: pop
    //   1171: sipush 400
    //   1174: istore_1
    //   1175: aload 83
    //   1177: invokevirtual 351	org/apache/http/client/methods/HttpGet:abort	()V
    //   1180: iload_2
    //   1181: istore 13
    //   1183: iconst_0
    //   1184: istore 15
    //   1186: iconst_0
    //   1187: istore 14
    //   1189: iconst_0
    //   1190: istore 11
    //   1192: aconst_null
    //   1193: astore 12
    //   1195: goto -518 -> 677
    //   1198: ldc 208
    //   1200: new 108	java/lang/StringBuilder
    //   1203: dup
    //   1204: invokespecial 109	java/lang/StringBuilder:<init>	()V
    //   1207: ldc_w 379
    //   1210: invokevirtual 118	java/lang/StringBuilder:append	(Ljava/lang/String;)Ljava/lang/StringBuilder;
    //   1213: aload_0
    //   1214: getfield 17	com/google/android/gm/downloadprovider/DownloadThread:mInfo	Lcom/google/android/gm/downloadprovider/DownloadInfo;
    //   1217: getfield 91	com/google/android/gm/downloadprovider/DownloadInfo:mId	I
    //   1220: invokevirtual 121	java/lang/StringBuilder:append	(I)Ljava/lang/StringBuilder;
    //   1223: ldc_w 377
    //   1226: invokevirtual 118	java/lang/StringBuilder:append	(Ljava/lang/String;)Ljava/lang/StringBuilder;
    //   1229: aload 102
    //   1231: invokevirtual 113	java/lang/StringBuilder:append	(Ljava/lang/Object;)Ljava/lang/StringBuilder;
    //   1234: invokevirtual 125	java/lang/StringBuilder:toString	()Ljava/lang/String;
    //   1237: invokestatic 362	android/util/Log:d	(Ljava/lang/String;Ljava/lang/String;)I
    //   1240: pop
    //   1241: goto -70 -> 1171
    //   1244: astore 27
    //   1246: aload 27
    //   1248: astore 28
    //   1250: iconst_0
    //   1251: istore 11
    //   1253: aconst_null
    //   1254: astore 12
    //   1256: iload_2
    //   1257: istore 13
    //   1259: iconst_0
    //   1260: istore 14
    //   1262: iconst_0
    //   1263: istore 15
    //   1265: getstatic 281	com/google/android/gm/downloadprovider/Constants:LOGV	Z
    //   1268: ifeq +3092 -> 4360
    //   1271: ldc 208
    //   1273: new 108	java/lang/StringBuilder
    //   1276: dup
    //   1277: invokespecial 109	java/lang/StringBuilder:<init>	()V
    //   1280: ldc_w 381
    //   1283: invokevirtual 118	java/lang/StringBuilder:append	(Ljava/lang/String;)Ljava/lang/StringBuilder;
    //   1286: aload_0
    //   1287: getfield 17	com/google/android/gm/downloadprovider/DownloadThread:mInfo	Lcom/google/android/gm/downloadprovider/DownloadInfo;
    //   1290: getfield 275	com/google/android/gm/downloadprovider/DownloadInfo:mUri	Ljava/lang/String;
    //   1293: invokevirtual 118	java/lang/StringBuilder:append	(Ljava/lang/String;)Ljava/lang/StringBuilder;
    //   1296: invokevirtual 125	java/lang/StringBuilder:toString	()Ljava/lang/String;
    //   1299: aload 28
    //   1301: invokestatic 384	android/util/Log:d	(Ljava/lang/String;Ljava/lang/String;Ljava/lang/Throwable;)I
    //   1304: pop
    //   1305: sipush 491
    //   1308: istore_1
    //   1309: aload_0
    //   1310: getfield 17	com/google/android/gm/downloadprovider/DownloadThread:mInfo	Lcom/google/android/gm/downloadprovider/DownloadInfo;
    //   1313: iconst_0
    //   1314: putfield 232	com/google/android/gm/downloadprovider/DownloadInfo:mHasActiveThread	Z
    //   1317: aload 7
    //   1319: ifnull +8 -> 1327
    //   1322: aload 7
    //   1324: invokevirtual 235	android/os/PowerManager$WakeLock:release	()V
    //   1327: aload 6
    //   1329: ifnull +8 -> 1337
    //   1332: aload 6
    //   1334: invokevirtual 240	android/net/http/AndroidHttpClient:close	()V
    //   1337: aload 5
    //   1339: ifnull +8 -> 1347
    //   1342: aload 5
    //   1344: invokevirtual 243	java/io/FileOutputStream:close	()V
    //   1347: aload_3
    //   1348: ifnull -608 -> 740
    //   1351: iload_1
    //   1352: invokestatic 246	com/google/android/gm/downloadprovider/Downloads$Impl:isStatusError	(I)Z
    //   1355: ifeq +3499 -> 4854
    //   1358: new 248	java/io/File
    //   1361: dup
    //   1362: aload_3
    //   1363: invokespecial 251	java/io/File:<init>	(Ljava/lang/String;)V
    //   1366: invokevirtual 255	java/io/File:delete	()Z
    //   1369: pop
    //   1370: aconst_null
    //   1371: astore_3
    //   1372: goto -632 -> 740
    //   1375: astore 84
    //   1377: aload_0
    //   1378: getfield 15	com/google/android/gm/downloadprovider/DownloadThread:mContext	Landroid/content/Context;
    //   1381: invokestatic 388	com/google/android/gm/downloadprovider/Helpers:isNetworkAvailable	(Landroid/content/Context;)Z
    //   1384: istore 85
    //   1386: iload 85
    //   1388: ifne +30 -> 1418
    //   1391: sipush 193
    //   1394: istore_1
    //   1395: iconst_0
    //   1396: istore 15
    //   1398: aload 83
    //   1400: invokevirtual 351	org/apache/http/client/methods/HttpGet:abort	()V
    //   1403: iload_2
    //   1404: istore 13
    //   1406: iconst_0
    //   1407: istore 14
    //   1409: iconst_0
    //   1410: istore 11
    //   1412: aconst_null
    //   1413: astore 12
    //   1415: goto -738 -> 677
    //   1418: aload_0
    //   1419: getfield 17	com/google/android/gm/downloadprovider/DownloadThread:mInfo	Lcom/google/android/gm/downloadprovider/DownloadInfo;
    //   1422: getfield 106	com/google/android/gm/downloadprovider/DownloadInfo:mNumFailed	I
    //   1425: iconst_5
    //   1426: if_icmpge +13 -> 1439
    //   1429: sipush 193
    //   1432: istore_1
    //   1433: iconst_1
    //   1434: istore 15
    //   1436: goto -38 -> 1398
    //   1439: getstatic 281	com/google/android/gm/downloadprovider/Constants:LOGV	Z
    //   1442: ifeq +49 -> 1491
    //   1445: ldc 208
    //   1447: new 108	java/lang/StringBuilder
    //   1450: dup
    //   1451: invokespecial 109	java/lang/StringBuilder:<init>	()V
    //   1454: ldc_w 390
    //   1457: invokevirtual 118	java/lang/StringBuilder:append	(Ljava/lang/String;)Ljava/lang/StringBuilder;
    //   1460: aload_0
    //   1461: getfield 17	com/google/android/gm/downloadprovider/DownloadThread:mInfo	Lcom/google/android/gm/downloadprovider/DownloadInfo;
    //   1464: getfield 275	com/google/android/gm/downloadprovider/DownloadInfo:mUri	Ljava/lang/String;
    //   1467: invokevirtual 118	java/lang/StringBuilder:append	(Ljava/lang/String;)Ljava/lang/StringBuilder;
    //   1470: ldc_w 377
    //   1473: invokevirtual 118	java/lang/StringBuilder:append	(Ljava/lang/String;)Ljava/lang/StringBuilder;
    //   1476: aload 84
    //   1478: invokevirtual 113	java/lang/StringBuilder:append	(Ljava/lang/Object;)Ljava/lang/StringBuilder;
    //   1481: invokevirtual 125	java/lang/StringBuilder:toString	()Ljava/lang/String;
    //   1484: invokestatic 362	android/util/Log:d	(Ljava/lang/String;Ljava/lang/String;)I
    //   1487: pop
    //   1488: goto +4576 -> 6064
    //   1491: ldc 208
    //   1493: new 108	java/lang/StringBuilder
    //   1496: dup
    //   1497: invokespecial 109	java/lang/StringBuilder:<init>	()V
    //   1500: ldc_w 390
    //   1503: invokevirtual 118	java/lang/StringBuilder:append	(Ljava/lang/String;)Ljava/lang/StringBuilder;
    //   1506: aload_0
    //   1507: getfield 17	com/google/android/gm/downloadprovider/DownloadThread:mInfo	Lcom/google/android/gm/downloadprovider/DownloadInfo;
    //   1510: getfield 91	com/google/android/gm/downloadprovider/DownloadInfo:mId	I
    //   1513: invokevirtual 121	java/lang/StringBuilder:append	(I)Ljava/lang/StringBuilder;
    //   1516: ldc_w 377
    //   1519: invokevirtual 118	java/lang/StringBuilder:append	(Ljava/lang/String;)Ljava/lang/StringBuilder;
    //   1522: aload 84
    //   1524: invokevirtual 113	java/lang/StringBuilder:append	(Ljava/lang/Object;)Ljava/lang/StringBuilder;
    //   1527: invokevirtual 125	java/lang/StringBuilder:toString	()Ljava/lang/String;
    //   1530: invokestatic 362	android/util/Log:d	(Ljava/lang/String;Ljava/lang/String;)I
    //   1533: pop
    //   1534: goto +4530 -> 6064
    //   1537: astore 9
    //   1539: aload 9
    //   1541: astore 10
    //   1543: iconst_0
    //   1544: istore 11
    //   1546: aconst_null
    //   1547: astore 12
    //   1549: iload_2
    //   1550: istore 13
    //   1552: iconst_0
    //   1553: istore 14
    //   1555: iconst_0
    //   1556: istore 15
    //   1558: aload_0
    //   1559: getfield 17	com/google/android/gm/downloadprovider/DownloadThread:mInfo	Lcom/google/android/gm/downloadprovider/DownloadInfo;
    //   1562: iconst_0
    //   1563: putfield 232	com/google/android/gm/downloadprovider/DownloadInfo:mHasActiveThread	Z
    //   1566: aload 7
    //   1568: ifnull +8 -> 1576
    //   1571: aload 7
    //   1573: invokevirtual 235	android/os/PowerManager$WakeLock:release	()V
    //   1576: aload 6
    //   1578: ifnull +8 -> 1586
    //   1581: aload 6
    //   1583: invokevirtual 240	android/net/http/AndroidHttpClient:close	()V
    //   1586: aload 5
    //   1588: ifnull +8 -> 1596
    //   1591: aload 5
    //   1593: invokevirtual 243	java/io/FileOutputStream:close	()V
    //   1596: aload_3
    //   1597: ifnull +24 -> 1621
    //   1600: iload_1
    //   1601: invokestatic 246	com/google/android/gm/downloadprovider/Downloads$Impl:isStatusError	(I)Z
    //   1604: ifeq +2840 -> 4444
    //   1607: new 248	java/io/File
    //   1610: dup
    //   1611: aload_3
    //   1612: invokespecial 251	java/io/File:<init>	(Ljava/lang/String;)V
    //   1615: invokevirtual 255	java/io/File:delete	()Z
    //   1618: pop
    //   1619: aconst_null
    //   1620: astore_3
    //   1621: aload_0
    //   1622: iload_1
    //   1623: iload 15
    //   1625: iload 14
    //   1627: iload 13
    //   1629: iload 11
    //   1631: aload_3
    //   1632: aload 12
    //   1634: aload 4
    //   1636: invokespecial 228	com/google/android/gm/downloadprovider/DownloadThread:notifyDownloadCompleted	(IZIIZLjava/lang/String;Ljava/lang/String;Ljava/lang/String;)V
    //   1639: aload 10
    //   1641: athrow
    //   1642: iload 14
    //   1644: bipush 30
    //   1646: if_icmpge +31 -> 1677
    //   1649: bipush 30
    //   1651: istore 14
    //   1653: getstatic 394	com/google/android/gm/downloadprovider/Helpers:sRandom	Ljava/util/Random;
    //   1656: bipush 31
    //   1658: invokevirtual 399	java/util/Random:nextInt	(I)I
    //   1661: istore 206
    //   1663: sipush 1000
    //   1666: iload 14
    //   1668: iload 206
    //   1670: iadd
    //   1671: imul
    //   1672: istore 14
    //   1674: goto -1011 -> 663
    //   1677: iload 14
    //   1679: ldc_w 400
    //   1682: if_icmple -29 -> 1653
    //   1685: ldc_w 400
    //   1688: istore 14
    //   1690: goto -37 -> 1653
    //   1693: iload 106
    //   1695: sipush 301
    //   1698: if_icmpeq +27 -> 1725
    //   1701: iload 106
    //   1703: sipush 302
    //   1706: if_icmpeq +19 -> 1725
    //   1709: iload 106
    //   1711: sipush 303
    //   1714: if_icmpeq +11 -> 1725
    //   1717: iload 106
    //   1719: sipush 307
    //   1722: if_icmpne +4352 -> 6074
    //   1725: getstatic 329	com/google/android/gm/downloadprovider/Constants:LOGVV	Z
    //   1728: ifeq +30 -> 1758
    //   1731: ldc 208
    //   1733: new 108	java/lang/StringBuilder
    //   1736: dup
    //   1737: invokespecial 109	java/lang/StringBuilder:<init>	()V
    //   1740: ldc_w 402
    //   1743: invokevirtual 118	java/lang/StringBuilder:append	(Ljava/lang/String;)Ljava/lang/StringBuilder;
    //   1746: iload 106
    //   1748: invokevirtual 121	java/lang/StringBuilder:append	(I)Ljava/lang/StringBuilder;
    //   1751: invokevirtual 125	java/lang/StringBuilder:toString	()Ljava/lang/String;
    //   1754: invokestatic 289	android/util/Log:v	(Ljava/lang/String;Ljava/lang/String;)I
    //   1757: pop
    //   1758: iload_2
    //   1759: iconst_5
    //   1760: if_icmplt +119 -> 1879
    //   1763: getstatic 281	com/google/android/gm/downloadprovider/Constants:LOGV	Z
    //   1766: ifeq +78 -> 1844
    //   1769: ldc 208
    //   1771: new 108	java/lang/StringBuilder
    //   1774: dup
    //   1775: invokespecial 109	java/lang/StringBuilder:<init>	()V
    //   1778: ldc_w 404
    //   1781: invokevirtual 118	java/lang/StringBuilder:append	(Ljava/lang/String;)Ljava/lang/StringBuilder;
    //   1784: aload_0
    //   1785: getfield 17	com/google/android/gm/downloadprovider/DownloadThread:mInfo	Lcom/google/android/gm/downloadprovider/DownloadInfo;
    //   1788: getfield 91	com/google/android/gm/downloadprovider/DownloadInfo:mId	I
    //   1791: invokevirtual 121	java/lang/StringBuilder:append	(I)Ljava/lang/StringBuilder;
    //   1794: ldc_w 406
    //   1797: invokevirtual 118	java/lang/StringBuilder:append	(Ljava/lang/String;)Ljava/lang/StringBuilder;
    //   1800: aload_0
    //   1801: getfield 17	com/google/android/gm/downloadprovider/DownloadThread:mInfo	Lcom/google/android/gm/downloadprovider/DownloadInfo;
    //   1804: getfield 275	com/google/android/gm/downloadprovider/DownloadInfo:mUri	Ljava/lang/String;
    //   1807: invokevirtual 118	java/lang/StringBuilder:append	(Ljava/lang/String;)Ljava/lang/StringBuilder;
    //   1810: invokevirtual 125	java/lang/StringBuilder:toString	()Ljava/lang/String;
    //   1813: invokestatic 362	android/util/Log:d	(Ljava/lang/String;Ljava/lang/String;)I
    //   1816: pop
    //   1817: sipush 497
    //   1820: istore_1
    //   1821: aload 83
    //   1823: invokevirtual 351	org/apache/http/client/methods/HttpGet:abort	()V
    //   1826: iload_2
    //   1827: istore 13
    //   1829: iconst_0
    //   1830: istore 15
    //   1832: iconst_0
    //   1833: istore 14
    //   1835: iconst_0
    //   1836: istore 11
    //   1838: aconst_null
    //   1839: astore 12
    //   1841: goto -1164 -> 677
    //   1844: ldc 208
    //   1846: new 108	java/lang/StringBuilder
    //   1849: dup
    //   1850: invokespecial 109	java/lang/StringBuilder:<init>	()V
    //   1853: ldc_w 404
    //   1856: invokevirtual 118	java/lang/StringBuilder:append	(Ljava/lang/String;)Ljava/lang/StringBuilder;
    //   1859: aload_0
    //   1860: getfield 17	com/google/android/gm/downloadprovider/DownloadThread:mInfo	Lcom/google/android/gm/downloadprovider/DownloadInfo;
    //   1863: getfield 91	com/google/android/gm/downloadprovider/DownloadInfo:mId	I
    //   1866: invokevirtual 121	java/lang/StringBuilder:append	(I)Ljava/lang/StringBuilder;
    //   1869: invokevirtual 125	java/lang/StringBuilder:toString	()Ljava/lang/String;
    //   1872: invokestatic 362	android/util/Log:d	(Ljava/lang/String;Ljava/lang/String;)I
    //   1875: pop
    //   1876: goto -59 -> 1817
    //   1879: aload 105
    //   1881: ldc_w 408
    //   1884: invokeinterface 337 2 0
    //   1889: astore 109
    //   1891: aload 109
    //   1893: ifnull +4181 -> 6074
    //   1896: getstatic 329	com/google/android/gm/downloadprovider/Constants:LOGVV	Z
    //   1899: ifeq +35 -> 1934
    //   1902: ldc 208
    //   1904: new 108	java/lang/StringBuilder
    //   1907: dup
    //   1908: invokespecial 109	java/lang/StringBuilder:<init>	()V
    //   1911: ldc_w 410
    //   1914: invokevirtual 118	java/lang/StringBuilder:append	(Ljava/lang/String;)Ljava/lang/StringBuilder;
    //   1917: aload 109
    //   1919: invokeinterface 344 1 0
    //   1924: invokevirtual 118	java/lang/StringBuilder:append	(Ljava/lang/String;)Ljava/lang/StringBuilder;
    //   1927: invokevirtual 125	java/lang/StringBuilder:toString	()Ljava/lang/String;
    //   1930: invokestatic 289	android/util/Log:v	(Ljava/lang/String;Ljava/lang/String;)I
    //   1933: pop
    //   1934: new 412	java/net/URI
    //   1937: dup
    //   1938: aload_0
    //   1939: getfield 17	com/google/android/gm/downloadprovider/DownloadThread:mInfo	Lcom/google/android/gm/downloadprovider/DownloadInfo;
    //   1942: getfield 275	com/google/android/gm/downloadprovider/DownloadInfo:mUri	Ljava/lang/String;
    //   1945: invokespecial 413	java/net/URI:<init>	(Ljava/lang/String;)V
    //   1948: new 412	java/net/URI
    //   1951: dup
    //   1952: aload 109
    //   1954: invokeinterface 344 1 0
    //   1959: invokespecial 413	java/net/URI:<init>	(Ljava/lang/String;)V
    //   1962: invokevirtual 417	java/net/URI:resolve	(Ljava/net/URI;)Ljava/net/URI;
    //   1965: invokevirtual 418	java/net/URI:toString	()Ljava/lang/String;
    //   1968: astore 113
    //   1970: aload 113
    //   1972: astore 12
    //   1974: iload_2
    //   1975: iconst_1
    //   1976: iadd
    //   1977: istore 13
    //   1979: sipush 193
    //   1982: istore_1
    //   1983: aload 83
    //   1985: invokevirtual 351	org/apache/http/client/methods/HttpGet:abort	()V
    //   1988: iconst_0
    //   1989: istore 15
    //   1991: iconst_0
    //   1992: istore 14
    //   1994: iconst_0
    //   1995: istore 11
    //   1997: goto -1320 -> 677
    //   2000: astore 110
    //   2002: getstatic 281	com/google/android/gm/downloadprovider/Constants:LOGV	Z
    //   2005: ifeq +78 -> 2083
    //   2008: ldc 208
    //   2010: new 108	java/lang/StringBuilder
    //   2013: dup
    //   2014: invokespecial 109	java/lang/StringBuilder:<init>	()V
    //   2017: ldc_w 420
    //   2020: invokevirtual 118	java/lang/StringBuilder:append	(Ljava/lang/String;)Ljava/lang/StringBuilder;
    //   2023: aload 109
    //   2025: invokeinterface 344 1 0
    //   2030: invokevirtual 118	java/lang/StringBuilder:append	(Ljava/lang/String;)Ljava/lang/StringBuilder;
    //   2033: ldc_w 422
    //   2036: invokevirtual 118	java/lang/StringBuilder:append	(Ljava/lang/String;)Ljava/lang/StringBuilder;
    //   2039: aload_0
    //   2040: getfield 17	com/google/android/gm/downloadprovider/DownloadThread:mInfo	Lcom/google/android/gm/downloadprovider/DownloadInfo;
    //   2043: getfield 275	com/google/android/gm/downloadprovider/DownloadInfo:mUri	Ljava/lang/String;
    //   2046: invokevirtual 118	java/lang/StringBuilder:append	(Ljava/lang/String;)Ljava/lang/StringBuilder;
    //   2049: invokevirtual 125	java/lang/StringBuilder:toString	()Ljava/lang/String;
    //   2052: invokestatic 362	android/util/Log:d	(Ljava/lang/String;Ljava/lang/String;)I
    //   2055: pop
    //   2056: sipush 400
    //   2059: istore_1
    //   2060: aload 83
    //   2062: invokevirtual 351	org/apache/http/client/methods/HttpGet:abort	()V
    //   2065: iload_2
    //   2066: istore 13
    //   2068: iconst_0
    //   2069: istore 15
    //   2071: iconst_0
    //   2072: istore 14
    //   2074: iconst_0
    //   2075: istore 11
    //   2077: aconst_null
    //   2078: astore 12
    //   2080: goto -1403 -> 677
    //   2083: ldc 208
    //   2085: new 108	java/lang/StringBuilder
    //   2088: dup
    //   2089: invokespecial 109	java/lang/StringBuilder:<init>	()V
    //   2092: ldc_w 424
    //   2095: invokevirtual 118	java/lang/StringBuilder:append	(Ljava/lang/String;)Ljava/lang/StringBuilder;
    //   2098: aload_0
    //   2099: getfield 17	com/google/android/gm/downloadprovider/DownloadThread:mInfo	Lcom/google/android/gm/downloadprovider/DownloadInfo;
    //   2102: getfield 91	com/google/android/gm/downloadprovider/DownloadInfo:mId	I
    //   2105: invokevirtual 121	java/lang/StringBuilder:append	(I)Ljava/lang/StringBuilder;
    //   2108: invokevirtual 125	java/lang/StringBuilder:toString	()Ljava/lang/String;
    //   2111: invokestatic 362	android/util/Log:d	(Ljava/lang/String;Ljava/lang/String;)I
    //   2114: pop
    //   2115: goto -59 -> 2056
    //   2118: getstatic 281	com/google/android/gm/downloadprovider/Constants:LOGV	Z
    //   2121: ifeq +80 -> 2201
    //   2124: ldc 208
    //   2126: new 108	java/lang/StringBuilder
    //   2129: dup
    //   2130: invokespecial 109	java/lang/StringBuilder:<init>	()V
    //   2133: ldc_w 426
    //   2136: invokevirtual 118	java/lang/StringBuilder:append	(Ljava/lang/String;)Ljava/lang/StringBuilder;
    //   2139: iload 106
    //   2141: invokevirtual 121	java/lang/StringBuilder:append	(I)Ljava/lang/StringBuilder;
    //   2144: ldc_w 422
    //   2147: invokevirtual 118	java/lang/StringBuilder:append	(Ljava/lang/String;)Ljava/lang/StringBuilder;
    //   2150: aload_0
    //   2151: getfield 17	com/google/android/gm/downloadprovider/DownloadThread:mInfo	Lcom/google/android/gm/downloadprovider/DownloadInfo;
    //   2154: getfield 275	com/google/android/gm/downloadprovider/DownloadInfo:mUri	Ljava/lang/String;
    //   2157: invokevirtual 118	java/lang/StringBuilder:append	(Ljava/lang/String;)Ljava/lang/StringBuilder;
    //   2160: invokevirtual 125	java/lang/StringBuilder:toString	()Ljava/lang/String;
    //   2163: invokestatic 362	android/util/Log:d	(Ljava/lang/String;Ljava/lang/String;)I
    //   2166: pop
    //   2167: iload 106
    //   2169: invokestatic 246	com/google/android/gm/downloadprovider/Downloads$Impl:isStatusError	(I)Z
    //   2172: ifeq +3931 -> 6103
    //   2175: iload 106
    //   2177: istore_1
    //   2178: aload 83
    //   2180: invokevirtual 351	org/apache/http/client/methods/HttpGet:abort	()V
    //   2183: iload_2
    //   2184: istore 13
    //   2186: iconst_0
    //   2187: istore 15
    //   2189: iconst_0
    //   2190: istore 14
    //   2192: iconst_0
    //   2193: istore 11
    //   2195: aconst_null
    //   2196: astore 12
    //   2198: goto -1521 -> 677
    //   2201: ldc 208
    //   2203: new 108	java/lang/StringBuilder
    //   2206: dup
    //   2207: invokespecial 109	java/lang/StringBuilder:<init>	()V
    //   2210: ldc_w 426
    //   2213: invokevirtual 118	java/lang/StringBuilder:append	(Ljava/lang/String;)Ljava/lang/StringBuilder;
    //   2216: iload 106
    //   2218: invokevirtual 121	java/lang/StringBuilder:append	(I)Ljava/lang/StringBuilder;
    //   2221: ldc_w 428
    //   2224: invokevirtual 118	java/lang/StringBuilder:append	(Ljava/lang/String;)Ljava/lang/StringBuilder;
    //   2227: aload_0
    //   2228: getfield 17	com/google/android/gm/downloadprovider/DownloadThread:mInfo	Lcom/google/android/gm/downloadprovider/DownloadInfo;
    //   2231: getfield 91	com/google/android/gm/downloadprovider/DownloadInfo:mId	I
    //   2234: invokevirtual 121	java/lang/StringBuilder:append	(I)Ljava/lang/StringBuilder;
    //   2237: invokevirtual 125	java/lang/StringBuilder:toString	()Ljava/lang/String;
    //   2240: invokestatic 362	android/util/Log:d	(Ljava/lang/String;Ljava/lang/String;)I
    //   2243: pop
    //   2244: goto -77 -> 2167
    //   2247: getstatic 281	com/google/android/gm/downloadprovider/Constants:LOGV	Z
    //   2250: ifeq +35 -> 2285
    //   2253: ldc 208
    //   2255: new 108	java/lang/StringBuilder
    //   2258: dup
    //   2259: invokespecial 109	java/lang/StringBuilder:<init>	()V
    //   2262: ldc_w 430
    //   2265: invokevirtual 118	java/lang/StringBuilder:append	(Ljava/lang/String;)Ljava/lang/StringBuilder;
    //   2268: aload_0
    //   2269: getfield 17	com/google/android/gm/downloadprovider/DownloadThread:mInfo	Lcom/google/android/gm/downloadprovider/DownloadInfo;
    //   2272: getfield 275	com/google/android/gm/downloadprovider/DownloadInfo:mUri	Ljava/lang/String;
    //   2275: invokevirtual 118	java/lang/StringBuilder:append	(Ljava/lang/String;)Ljava/lang/StringBuilder;
    //   2278: invokevirtual 125	java/lang/StringBuilder:toString	()Ljava/lang/String;
    //   2281: invokestatic 289	android/util/Log:v	(Ljava/lang/String;Ljava/lang/String;)I
    //   2284: pop
    //   2285: iload 59
    //   2287: ifne +746 -> 3033
    //   2290: aload 105
    //   2292: ldc_w 432
    //   2295: invokeinterface 337 2 0
    //   2300: astore 118
    //   2302: aconst_null
    //   2303: astore 119
    //   2305: aload 118
    //   2307: ifnull +12 -> 2319
    //   2310: aload 118
    //   2312: invokeinterface 344 1 0
    //   2317: astore 119
    //   2319: aload 105
    //   2321: ldc_w 434
    //   2324: invokeinterface 337 2 0
    //   2329: astore 120
    //   2331: aconst_null
    //   2332: astore 121
    //   2334: aload 120
    //   2336: ifnull +12 -> 2348
    //   2339: aload 120
    //   2341: invokeinterface 344 1 0
    //   2346: astore 121
    //   2348: aload 105
    //   2350: ldc_w 436
    //   2353: invokeinterface 337 2 0
    //   2358: astore 122
    //   2360: aconst_null
    //   2361: astore 123
    //   2363: aload 122
    //   2365: ifnull +12 -> 2377
    //   2368: aload 122
    //   2370: invokeinterface 344 1 0
    //   2375: astore 123
    //   2377: aload 4
    //   2379: ifnonnull +33 -> 2412
    //   2382: aload 105
    //   2384: ldc_w 438
    //   2387: invokeinterface 337 2 0
    //   2392: astore 124
    //   2394: aload 124
    //   2396: ifnull +16 -> 2412
    //   2399: aload_0
    //   2400: aload 124
    //   2402: invokeinterface 344 1 0
    //   2407: invokespecial 198	com/google/android/gm/downloadprovider/DownloadThread:sanitizeMimeType	(Ljava/lang/String;)Ljava/lang/String;
    //   2410: astore 4
    //   2412: aload 105
    //   2414: ldc_w 440
    //   2417: invokeinterface 337 2 0
    //   2422: astore 125
    //   2424: aload 125
    //   2426: ifnull +12 -> 2438
    //   2429: aload 125
    //   2431: invokeinterface 344 1 0
    //   2436: astore 61
    //   2438: aload 105
    //   2440: ldc_w 442
    //   2443: invokeinterface 337 2 0
    //   2448: astore 126
    //   2450: aconst_null
    //   2451: astore 127
    //   2453: aload 126
    //   2455: ifnull +12 -> 2467
    //   2458: aload 126
    //   2460: invokeinterface 344 1 0
    //   2465: astore 127
    //   2467: aload 127
    //   2469: ifnonnull +291 -> 2760
    //   2472: aload 105
    //   2474: ldc_w 444
    //   2477: invokeinterface 337 2 0
    //   2482: astore 128
    //   2484: aload 128
    //   2486: ifnull +12 -> 2498
    //   2489: aload 128
    //   2491: invokeinterface 344 1 0
    //   2496: astore 60
    //   2498: getstatic 329	com/google/android/gm/downloadprovider/Constants:LOGVV	Z
    //   2501: ifeq +192 -> 2693
    //   2504: ldc 208
    //   2506: new 108	java/lang/StringBuilder
    //   2509: dup
    //   2510: invokespecial 109	java/lang/StringBuilder:<init>	()V
    //   2513: ldc_w 446
    //   2516: invokevirtual 118	java/lang/StringBuilder:append	(Ljava/lang/String;)Ljava/lang/StringBuilder;
    //   2519: aload 119
    //   2521: invokevirtual 118	java/lang/StringBuilder:append	(Ljava/lang/String;)Ljava/lang/StringBuilder;
    //   2524: invokevirtual 125	java/lang/StringBuilder:toString	()Ljava/lang/String;
    //   2527: invokestatic 289	android/util/Log:v	(Ljava/lang/String;Ljava/lang/String;)I
    //   2530: pop
    //   2531: ldc 208
    //   2533: new 108	java/lang/StringBuilder
    //   2536: dup
    //   2537: invokespecial 109	java/lang/StringBuilder:<init>	()V
    //   2540: ldc_w 448
    //   2543: invokevirtual 118	java/lang/StringBuilder:append	(Ljava/lang/String;)Ljava/lang/StringBuilder;
    //   2546: aload 121
    //   2548: invokevirtual 118	java/lang/StringBuilder:append	(Ljava/lang/String;)Ljava/lang/StringBuilder;
    //   2551: invokevirtual 125	java/lang/StringBuilder:toString	()Ljava/lang/String;
    //   2554: invokestatic 289	android/util/Log:v	(Ljava/lang/String;Ljava/lang/String;)I
    //   2557: pop
    //   2558: ldc 208
    //   2560: new 108	java/lang/StringBuilder
    //   2563: dup
    //   2564: invokespecial 109	java/lang/StringBuilder:<init>	()V
    //   2567: ldc_w 450
    //   2570: invokevirtual 118	java/lang/StringBuilder:append	(Ljava/lang/String;)Ljava/lang/StringBuilder;
    //   2573: aload 60
    //   2575: invokevirtual 118	java/lang/StringBuilder:append	(Ljava/lang/String;)Ljava/lang/StringBuilder;
    //   2578: invokevirtual 125	java/lang/StringBuilder:toString	()Ljava/lang/String;
    //   2581: invokestatic 289	android/util/Log:v	(Ljava/lang/String;Ljava/lang/String;)I
    //   2584: pop
    //   2585: ldc 208
    //   2587: new 108	java/lang/StringBuilder
    //   2590: dup
    //   2591: invokespecial 109	java/lang/StringBuilder:<init>	()V
    //   2594: ldc_w 452
    //   2597: invokevirtual 118	java/lang/StringBuilder:append	(Ljava/lang/String;)Ljava/lang/StringBuilder;
    //   2600: aload 123
    //   2602: invokevirtual 118	java/lang/StringBuilder:append	(Ljava/lang/String;)Ljava/lang/StringBuilder;
    //   2605: invokevirtual 125	java/lang/StringBuilder:toString	()Ljava/lang/String;
    //   2608: invokestatic 289	android/util/Log:v	(Ljava/lang/String;Ljava/lang/String;)I
    //   2611: pop
    //   2612: ldc 208
    //   2614: new 108	java/lang/StringBuilder
    //   2617: dup
    //   2618: invokespecial 109	java/lang/StringBuilder:<init>	()V
    //   2621: ldc_w 454
    //   2624: invokevirtual 118	java/lang/StringBuilder:append	(Ljava/lang/String;)Ljava/lang/StringBuilder;
    //   2627: aload 4
    //   2629: invokevirtual 118	java/lang/StringBuilder:append	(Ljava/lang/String;)Ljava/lang/StringBuilder;
    //   2632: invokevirtual 125	java/lang/StringBuilder:toString	()Ljava/lang/String;
    //   2635: invokestatic 289	android/util/Log:v	(Ljava/lang/String;Ljava/lang/String;)I
    //   2638: pop
    //   2639: ldc 208
    //   2641: new 108	java/lang/StringBuilder
    //   2644: dup
    //   2645: invokespecial 109	java/lang/StringBuilder:<init>	()V
    //   2648: ldc_w 456
    //   2651: invokevirtual 118	java/lang/StringBuilder:append	(Ljava/lang/String;)Ljava/lang/StringBuilder;
    //   2654: aload 61
    //   2656: invokevirtual 118	java/lang/StringBuilder:append	(Ljava/lang/String;)Ljava/lang/StringBuilder;
    //   2659: invokevirtual 125	java/lang/StringBuilder:toString	()Ljava/lang/String;
    //   2662: invokestatic 289	android/util/Log:v	(Ljava/lang/String;Ljava/lang/String;)I
    //   2665: pop
    //   2666: ldc 208
    //   2668: new 108	java/lang/StringBuilder
    //   2671: dup
    //   2672: invokespecial 109	java/lang/StringBuilder:<init>	()V
    //   2675: ldc_w 458
    //   2678: invokevirtual 118	java/lang/StringBuilder:append	(Ljava/lang/String;)Ljava/lang/StringBuilder;
    //   2681: aload 127
    //   2683: invokevirtual 118	java/lang/StringBuilder:append	(Ljava/lang/String;)Ljava/lang/StringBuilder;
    //   2686: invokevirtual 125	java/lang/StringBuilder:toString	()Ljava/lang/String;
    //   2689: invokestatic 289	android/util/Log:v	(Ljava/lang/String;Ljava/lang/String;)I
    //   2692: pop
    //   2693: aload_0
    //   2694: getfield 17	com/google/android/gm/downloadprovider/DownloadThread:mInfo	Lcom/google/android/gm/downloadprovider/DownloadInfo;
    //   2697: getfield 357	com/google/android/gm/downloadprovider/DownloadInfo:mNoIntegrity	Z
    //   2700: ifne +78 -> 2778
    //   2703: aload 60
    //   2705: ifnonnull +73 -> 2778
    //   2708: aload 127
    //   2710: ifnull +14 -> 2724
    //   2713: aload 127
    //   2715: ldc_w 460
    //   2718: invokevirtual 464	java/lang/String:equalsIgnoreCase	(Ljava/lang/String;)Z
    //   2721: ifne +57 -> 2778
    //   2724: ldc 208
    //   2726: ldc_w 466
    //   2729: invokestatic 362	android/util/Log:d	(Ljava/lang/String;Ljava/lang/String;)I
    //   2732: pop
    //   2733: sipush 411
    //   2736: istore_1
    //   2737: aload 83
    //   2739: invokevirtual 351	org/apache/http/client/methods/HttpGet:abort	()V
    //   2742: iload_2
    //   2743: istore 13
    //   2745: iconst_0
    //   2746: istore 15
    //   2748: iconst_0
    //   2749: istore 14
    //   2751: iconst_0
    //   2752: istore 11
    //   2754: aconst_null
    //   2755: astore 12
    //   2757: goto -2080 -> 677
    //   2760: getstatic 329	com/google/android/gm/downloadprovider/Constants:LOGVV	Z
    //   2763: ifeq -265 -> 2498
    //   2766: ldc 208
    //   2768: ldc_w 468
    //   2771: invokestatic 289	android/util/Log:v	(Ljava/lang/String;Ljava/lang/String;)I
    //   2774: pop
    //   2775: goto -277 -> 2498
    //   2778: aload_0
    //   2779: getfield 15	com/google/android/gm/downloadprovider/DownloadThread:mContext	Landroid/content/Context;
    //   2782: astore 129
    //   2784: aload_0
    //   2785: getfield 17	com/google/android/gm/downloadprovider/DownloadThread:mInfo	Lcom/google/android/gm/downloadprovider/DownloadInfo;
    //   2788: getfield 275	com/google/android/gm/downloadprovider/DownloadInfo:mUri	Ljava/lang/String;
    //   2791: astore 130
    //   2793: aload_0
    //   2794: getfield 17	com/google/android/gm/downloadprovider/DownloadThread:mInfo	Lcom/google/android/gm/downloadprovider/DownloadInfo;
    //   2797: getfield 471	com/google/android/gm/downloadprovider/DownloadInfo:mHint	Ljava/lang/String;
    //   2800: astore 131
    //   2802: aload_0
    //   2803: getfield 17	com/google/android/gm/downloadprovider/DownloadThread:mInfo	Lcom/google/android/gm/downloadprovider/DownloadInfo;
    //   2806: getfield 270	com/google/android/gm/downloadprovider/DownloadInfo:mDestination	I
    //   2809: istore 132
    //   2811: aload 60
    //   2813: ifnull +3340 -> 6153
    //   2816: aload 60
    //   2818: invokestatic 348	java/lang/Integer:parseInt	(Ljava/lang/String;)I
    //   2821: istore 133
    //   2823: aload 129
    //   2825: aload 130
    //   2827: aload 131
    //   2829: aload 121
    //   2831: aload 123
    //   2833: aload 4
    //   2835: iload 132
    //   2837: iload 133
    //   2839: invokestatic 475	com/google/android/gm/downloadprovider/Helpers:generateSaveFile	(Landroid/content/Context;Ljava/lang/String;Ljava/lang/String;Ljava/lang/String;Ljava/lang/String;Ljava/lang/String;II)Lcom/google/android/gm/downloadprovider/DownloadFileInfo;
    //   2842: astore 134
    //   2844: aload 134
    //   2846: getfield 478	com/google/android/gm/downloadprovider/DownloadFileInfo:mFileName	Ljava/lang/String;
    //   2849: ifnonnull +32 -> 2881
    //   2852: aload 134
    //   2854: getfield 481	com/google/android/gm/downloadprovider/DownloadFileInfo:mStatus	I
    //   2857: istore_1
    //   2858: aload 83
    //   2860: invokevirtual 351	org/apache/http/client/methods/HttpGet:abort	()V
    //   2863: iload_2
    //   2864: istore 13
    //   2866: iconst_0
    //   2867: istore 15
    //   2869: iconst_0
    //   2870: istore 14
    //   2872: iconst_0
    //   2873: istore 11
    //   2875: aconst_null
    //   2876: astore 12
    //   2878: goto -2201 -> 677
    //   2881: aload 134
    //   2883: getfield 478	com/google/android/gm/downloadprovider/DownloadFileInfo:mFileName	Ljava/lang/String;
    //   2886: astore_3
    //   2887: aload 134
    //   2889: getfield 485	com/google/android/gm/downloadprovider/DownloadFileInfo:mStream	Ljava/io/FileOutputStream;
    //   2892: astore 5
    //   2894: getstatic 281	com/google/android/gm/downloadprovider/Constants:LOGV	Z
    //   2897: ifeq +45 -> 2942
    //   2900: ldc 208
    //   2902: new 108	java/lang/StringBuilder
    //   2905: dup
    //   2906: invokespecial 109	java/lang/StringBuilder:<init>	()V
    //   2909: ldc_w 487
    //   2912: invokevirtual 118	java/lang/StringBuilder:append	(Ljava/lang/String;)Ljava/lang/StringBuilder;
    //   2915: aload_0
    //   2916: getfield 17	com/google/android/gm/downloadprovider/DownloadThread:mInfo	Lcom/google/android/gm/downloadprovider/DownloadInfo;
    //   2919: getfield 275	com/google/android/gm/downloadprovider/DownloadInfo:mUri	Ljava/lang/String;
    //   2922: invokevirtual 118	java/lang/StringBuilder:append	(Ljava/lang/String;)Ljava/lang/StringBuilder;
    //   2925: ldc_w 489
    //   2928: invokevirtual 118	java/lang/StringBuilder:append	(Ljava/lang/String;)Ljava/lang/StringBuilder;
    //   2931: aload_3
    //   2932: invokevirtual 118	java/lang/StringBuilder:append	(Ljava/lang/String;)Ljava/lang/StringBuilder;
    //   2935: invokevirtual 125	java/lang/StringBuilder:toString	()Ljava/lang/String;
    //   2938: invokestatic 289	android/util/Log:v	(Ljava/lang/String;Ljava/lang/String;)I
    //   2941: pop
    //   2942: new 33	android/content/ContentValues
    //   2945: dup
    //   2946: invokespecial 34	android/content/ContentValues:<init>	()V
    //   2949: astore 135
    //   2951: aload 135
    //   2953: ldc 48
    //   2955: aload_3
    //   2956: invokevirtual 51	android/content/ContentValues:put	(Ljava/lang/String;Ljava/lang/String;)V
    //   2959: aload 61
    //   2961: ifnull +13 -> 2974
    //   2964: aload 135
    //   2966: ldc_w 491
    //   2969: aload 61
    //   2971: invokevirtual 51	android/content/ContentValues:put	(Ljava/lang/String;Ljava/lang/String;)V
    //   2974: aload 4
    //   2976: ifnull +12 -> 2988
    //   2979: aload 135
    //   2981: ldc 55
    //   2983: aload 4
    //   2985: invokevirtual 51	android/content/ContentValues:put	(Ljava/lang/String;Ljava/lang/String;)V
    //   2988: iconst_m1
    //   2989: istore 136
    //   2991: aload 60
    //   2993: ifnull +10 -> 3003
    //   2996: aload 60
    //   2998: invokestatic 348	java/lang/Integer:parseInt	(Ljava/lang/String;)I
    //   3001: istore 136
    //   3003: aload 135
    //   3005: ldc_w 493
    //   3008: iload 136
    //   3010: invokestatic 42	java/lang/Integer:valueOf	(I)Ljava/lang/Integer;
    //   3013: invokevirtual 46	android/content/ContentValues:put	(Ljava/lang/String;Ljava/lang/Integer;)V
    //   3016: aload_0
    //   3017: getfield 15	com/google/android/gm/downloadprovider/DownloadThread:mContext	Landroid/content/Context;
    //   3020: invokevirtual 81	android/content/Context:getContentResolver	()Landroid/content/ContentResolver;
    //   3023: aload 8
    //   3025: aload 135
    //   3027: aconst_null
    //   3028: aconst_null
    //   3029: invokevirtual 103	android/content/ContentResolver:update	(Landroid/net/Uri;Landroid/content/ContentValues;Ljava/lang/String;[Ljava/lang/String;)I
    //   3032: pop
    //   3033: aload 105
    //   3035: invokeinterface 497 1 0
    //   3040: invokeinterface 503 1 0
    //   3045: astore 142
    //   3047: iconst_0
    //   3048: istore 11
    //   3050: aload 142
    //   3052: aload 57
    //   3054: invokevirtual 509	java/io/InputStream:read	([B)I
    //   3057: istore 157
    //   3059: iload 157
    //   3061: iconst_m1
    //   3062: if_icmpne +806 -> 3868
    //   3065: new 33	android/content/ContentValues
    //   3068: dup
    //   3069: invokespecial 34	android/content/ContentValues:<init>	()V
    //   3072: astore 177
    //   3074: aload 177
    //   3076: ldc_w 511
    //   3079: iload 58
    //   3081: invokestatic 42	java/lang/Integer:valueOf	(I)Ljava/lang/Integer;
    //   3084: invokevirtual 46	android/content/ContentValues:put	(Ljava/lang/String;Ljava/lang/Integer;)V
    //   3087: aload 60
    //   3089: ifnonnull +16 -> 3105
    //   3092: aload 177
    //   3094: ldc_w 493
    //   3097: iload 58
    //   3099: invokestatic 42	java/lang/Integer:valueOf	(I)Ljava/lang/Integer;
    //   3102: invokevirtual 46	android/content/ContentValues:put	(Ljava/lang/String;Ljava/lang/Integer;)V
    //   3105: aload_0
    //   3106: getfield 15	com/google/android/gm/downloadprovider/DownloadThread:mContext	Landroid/content/Context;
    //   3109: invokevirtual 81	android/content/Context:getContentResolver	()Landroid/content/ContentResolver;
    //   3112: aload 8
    //   3114: aload 177
    //   3116: aconst_null
    //   3117: aconst_null
    //   3118: invokevirtual 103	android/content/ContentResolver:update	(Landroid/net/Uri;Landroid/content/ContentValues;Ljava/lang/String;[Ljava/lang/String;)I
    //   3121: pop
    //   3122: aload 60
    //   3124: ifnull +1179 -> 4303
    //   3127: aload 60
    //   3129: invokestatic 348	java/lang/Integer:parseInt	(Ljava/lang/String;)I
    //   3132: istore 179
    //   3134: iload 58
    //   3136: iload 179
    //   3138: if_icmpeq +1165 -> 4303
    //   3141: aload_0
    //   3142: getfield 17	com/google/android/gm/downloadprovider/DownloadThread:mInfo	Lcom/google/android/gm/downloadprovider/DownloadInfo;
    //   3145: getfield 357	com/google/android/gm/downloadprovider/DownloadInfo:mNoIntegrity	Z
    //   3148: ifne +585 -> 3733
    //   3151: aload 61
    //   3153: ifnonnull +580 -> 3733
    //   3156: getstatic 281	com/google/android/gm/downloadprovider/Constants:LOGV	Z
    //   3159: ifeq +539 -> 3698
    //   3162: ldc 208
    //   3164: new 108	java/lang/StringBuilder
    //   3167: dup
    //   3168: invokespecial 109	java/lang/StringBuilder:<init>	()V
    //   3171: ldc_w 513
    //   3174: invokevirtual 118	java/lang/StringBuilder:append	(Ljava/lang/String;)Ljava/lang/StringBuilder;
    //   3177: aload_0
    //   3178: getfield 17	com/google/android/gm/downloadprovider/DownloadThread:mInfo	Lcom/google/android/gm/downloadprovider/DownloadInfo;
    //   3181: getfield 275	com/google/android/gm/downloadprovider/DownloadInfo:mUri	Ljava/lang/String;
    //   3184: invokevirtual 118	java/lang/StringBuilder:append	(Ljava/lang/String;)Ljava/lang/StringBuilder;
    //   3187: invokevirtual 125	java/lang/StringBuilder:toString	()Ljava/lang/String;
    //   3190: invokestatic 362	android/util/Log:d	(Ljava/lang/String;Ljava/lang/String;)I
    //   3193: pop
    //   3194: sipush 411
    //   3197: istore_1
    //   3198: iload_2
    //   3199: istore 13
    //   3201: iconst_0
    //   3202: istore 15
    //   3204: iconst_0
    //   3205: istore 14
    //   3207: aconst_null
    //   3208: astore 12
    //   3210: goto -2533 -> 677
    //   3213: astore 138
    //   3215: aload_0
    //   3216: getfield 15	com/google/android/gm/downloadprovider/DownloadThread:mContext	Landroid/content/Context;
    //   3219: invokestatic 388	com/google/android/gm/downloadprovider/Helpers:isNetworkAvailable	(Landroid/content/Context;)Z
    //   3222: istore 139
    //   3224: iload 139
    //   3226: ifne +30 -> 3256
    //   3229: sipush 193
    //   3232: istore_1
    //   3233: iconst_0
    //   3234: istore 15
    //   3236: aload 83
    //   3238: invokevirtual 351	org/apache/http/client/methods/HttpGet:abort	()V
    //   3241: iload_2
    //   3242: istore 13
    //   3244: iconst_0
    //   3245: istore 14
    //   3247: iconst_0
    //   3248: istore 11
    //   3250: aconst_null
    //   3251: astore 12
    //   3253: goto -2576 -> 677
    //   3256: aload_0
    //   3257: getfield 17	com/google/android/gm/downloadprovider/DownloadThread:mInfo	Lcom/google/android/gm/downloadprovider/DownloadInfo;
    //   3260: getfield 106	com/google/android/gm/downloadprovider/DownloadInfo:mNumFailed	I
    //   3263: iconst_5
    //   3264: if_icmpge +13 -> 3277
    //   3267: sipush 193
    //   3270: istore_1
    //   3271: iconst_1
    //   3272: istore 15
    //   3274: goto -38 -> 3236
    //   3277: getstatic 281	com/google/android/gm/downloadprovider/Constants:LOGV	Z
    //   3280: ifeq +49 -> 3329
    //   3283: ldc 208
    //   3285: new 108	java/lang/StringBuilder
    //   3288: dup
    //   3289: invokespecial 109	java/lang/StringBuilder:<init>	()V
    //   3292: ldc_w 515
    //   3295: invokevirtual 118	java/lang/StringBuilder:append	(Ljava/lang/String;)Ljava/lang/StringBuilder;
    //   3298: aload_0
    //   3299: getfield 17	com/google/android/gm/downloadprovider/DownloadThread:mInfo	Lcom/google/android/gm/downloadprovider/DownloadInfo;
    //   3302: getfield 275	com/google/android/gm/downloadprovider/DownloadInfo:mUri	Ljava/lang/String;
    //   3305: invokevirtual 118	java/lang/StringBuilder:append	(Ljava/lang/String;)Ljava/lang/StringBuilder;
    //   3308: ldc_w 377
    //   3311: invokevirtual 118	java/lang/StringBuilder:append	(Ljava/lang/String;)Ljava/lang/StringBuilder;
    //   3314: aload 138
    //   3316: invokevirtual 113	java/lang/StringBuilder:append	(Ljava/lang/Object;)Ljava/lang/StringBuilder;
    //   3319: invokevirtual 125	java/lang/StringBuilder:toString	()Ljava/lang/String;
    //   3322: invokestatic 362	android/util/Log:d	(Ljava/lang/String;Ljava/lang/String;)I
    //   3325: pop
    //   3326: goto +2833 -> 6159
    //   3329: ldc 208
    //   3331: new 108	java/lang/StringBuilder
    //   3334: dup
    //   3335: invokespecial 109	java/lang/StringBuilder:<init>	()V
    //   3338: ldc_w 517
    //   3341: invokevirtual 118	java/lang/StringBuilder:append	(Ljava/lang/String;)Ljava/lang/StringBuilder;
    //   3344: aload_0
    //   3345: getfield 17	com/google/android/gm/downloadprovider/DownloadThread:mInfo	Lcom/google/android/gm/downloadprovider/DownloadInfo;
    //   3348: getfield 91	com/google/android/gm/downloadprovider/DownloadInfo:mId	I
    //   3351: invokevirtual 121	java/lang/StringBuilder:append	(I)Ljava/lang/StringBuilder;
    //   3354: ldc_w 377
    //   3357: invokevirtual 118	java/lang/StringBuilder:append	(Ljava/lang/String;)Ljava/lang/StringBuilder;
    //   3360: aload 138
    //   3362: invokevirtual 113	java/lang/StringBuilder:append	(Ljava/lang/Object;)Ljava/lang/StringBuilder;
    //   3365: invokevirtual 125	java/lang/StringBuilder:toString	()Ljava/lang/String;
    //   3368: invokestatic 362	android/util/Log:d	(Ljava/lang/String;Ljava/lang/String;)I
    //   3371: pop
    //   3372: goto +2787 -> 6159
    //   3375: astore 146
    //   3377: new 33	android/content/ContentValues
    //   3380: dup
    //   3381: invokespecial 34	android/content/ContentValues:<init>	()V
    //   3384: astore 147
    //   3386: aload 147
    //   3388: ldc_w 511
    //   3391: iload 58
    //   3393: invokestatic 42	java/lang/Integer:valueOf	(I)Ljava/lang/Integer;
    //   3396: invokevirtual 46	android/content/ContentValues:put	(Ljava/lang/String;Ljava/lang/Integer;)V
    //   3399: aload_0
    //   3400: getfield 15	com/google/android/gm/downloadprovider/DownloadThread:mContext	Landroid/content/Context;
    //   3403: invokevirtual 81	android/content/Context:getContentResolver	()Landroid/content/ContentResolver;
    //   3406: aload 8
    //   3408: aload 147
    //   3410: aconst_null
    //   3411: aconst_null
    //   3412: invokevirtual 103	android/content/ContentResolver:update	(Landroid/net/Uri;Landroid/content/ContentValues;Ljava/lang/String;[Ljava/lang/String;)I
    //   3415: pop
    //   3416: aload_0
    //   3417: getfield 17	com/google/android/gm/downloadprovider/DownloadThread:mInfo	Lcom/google/android/gm/downloadprovider/DownloadInfo;
    //   3420: getfield 357	com/google/android/gm/downloadprovider/DownloadInfo:mNoIntegrity	Z
    //   3423: ifne +136 -> 3559
    //   3426: aload 61
    //   3428: ifnonnull +131 -> 3559
    //   3431: getstatic 281	com/google/android/gm/downloadprovider/Constants:LOGV	Z
    //   3434: ifeq +79 -> 3513
    //   3437: ldc 208
    //   3439: new 108	java/lang/StringBuilder
    //   3442: dup
    //   3443: invokespecial 109	java/lang/StringBuilder:<init>	()V
    //   3446: ldc_w 519
    //   3449: invokevirtual 118	java/lang/StringBuilder:append	(Ljava/lang/String;)Ljava/lang/StringBuilder;
    //   3452: aload_0
    //   3453: getfield 17	com/google/android/gm/downloadprovider/DownloadThread:mInfo	Lcom/google/android/gm/downloadprovider/DownloadInfo;
    //   3456: getfield 275	com/google/android/gm/downloadprovider/DownloadInfo:mUri	Ljava/lang/String;
    //   3459: invokevirtual 118	java/lang/StringBuilder:append	(Ljava/lang/String;)Ljava/lang/StringBuilder;
    //   3462: ldc_w 377
    //   3465: invokevirtual 118	java/lang/StringBuilder:append	(Ljava/lang/String;)Ljava/lang/StringBuilder;
    //   3468: aload 146
    //   3470: invokevirtual 113	java/lang/StringBuilder:append	(Ljava/lang/Object;)Ljava/lang/StringBuilder;
    //   3473: invokevirtual 125	java/lang/StringBuilder:toString	()Ljava/lang/String;
    //   3476: invokestatic 289	android/util/Log:v	(Ljava/lang/String;Ljava/lang/String;)I
    //   3479: pop
    //   3480: ldc 208
    //   3482: ldc_w 521
    //   3485: invokestatic 362	android/util/Log:d	(Ljava/lang/String;Ljava/lang/String;)I
    //   3488: pop
    //   3489: sipush 412
    //   3492: istore_1
    //   3493: iconst_0
    //   3494: istore 15
    //   3496: aload 83
    //   3498: invokevirtual 351	org/apache/http/client/methods/HttpGet:abort	()V
    //   3501: iload_2
    //   3502: istore 13
    //   3504: iconst_0
    //   3505: istore 14
    //   3507: aconst_null
    //   3508: astore 12
    //   3510: goto -2833 -> 677
    //   3513: ldc 208
    //   3515: new 108	java/lang/StringBuilder
    //   3518: dup
    //   3519: invokespecial 109	java/lang/StringBuilder:<init>	()V
    //   3522: ldc_w 523
    //   3525: invokevirtual 118	java/lang/StringBuilder:append	(Ljava/lang/String;)Ljava/lang/StringBuilder;
    //   3528: aload_0
    //   3529: getfield 17	com/google/android/gm/downloadprovider/DownloadThread:mInfo	Lcom/google/android/gm/downloadprovider/DownloadInfo;
    //   3532: getfield 91	com/google/android/gm/downloadprovider/DownloadInfo:mId	I
    //   3535: invokevirtual 121	java/lang/StringBuilder:append	(I)Ljava/lang/StringBuilder;
    //   3538: ldc_w 377
    //   3541: invokevirtual 118	java/lang/StringBuilder:append	(Ljava/lang/String;)Ljava/lang/StringBuilder;
    //   3544: aload 146
    //   3546: invokevirtual 113	java/lang/StringBuilder:append	(Ljava/lang/Object;)Ljava/lang/StringBuilder;
    //   3549: invokevirtual 125	java/lang/StringBuilder:toString	()Ljava/lang/String;
    //   3552: invokestatic 362	android/util/Log:d	(Ljava/lang/String;Ljava/lang/String;)I
    //   3555: pop
    //   3556: goto -76 -> 3480
    //   3559: aload_0
    //   3560: getfield 15	com/google/android/gm/downloadprovider/DownloadThread:mContext	Landroid/content/Context;
    //   3563: invokestatic 388	com/google/android/gm/downloadprovider/Helpers:isNetworkAvailable	(Landroid/content/Context;)Z
    //   3566: ifne +13 -> 3579
    //   3569: sipush 193
    //   3572: istore_1
    //   3573: iconst_0
    //   3574: istore 15
    //   3576: goto -80 -> 3496
    //   3579: aload_0
    //   3580: getfield 17	com/google/android/gm/downloadprovider/DownloadThread:mInfo	Lcom/google/android/gm/downloadprovider/DownloadInfo;
    //   3583: getfield 106	com/google/android/gm/downloadprovider/DownloadInfo:mNumFailed	I
    //   3586: iconst_5
    //   3587: if_icmpge +13 -> 3600
    //   3590: sipush 193
    //   3593: istore_1
    //   3594: iconst_1
    //   3595: istore 15
    //   3597: goto -101 -> 3496
    //   3600: getstatic 281	com/google/android/gm/downloadprovider/Constants:LOGV	Z
    //   3603: ifeq +49 -> 3652
    //   3606: ldc 208
    //   3608: new 108	java/lang/StringBuilder
    //   3611: dup
    //   3612: invokespecial 109	java/lang/StringBuilder:<init>	()V
    //   3615: ldc_w 519
    //   3618: invokevirtual 118	java/lang/StringBuilder:append	(Ljava/lang/String;)Ljava/lang/StringBuilder;
    //   3621: aload_0
    //   3622: getfield 17	com/google/android/gm/downloadprovider/DownloadThread:mInfo	Lcom/google/android/gm/downloadprovider/DownloadInfo;
    //   3625: getfield 275	com/google/android/gm/downloadprovider/DownloadInfo:mUri	Ljava/lang/String;
    //   3628: invokevirtual 118	java/lang/StringBuilder:append	(Ljava/lang/String;)Ljava/lang/StringBuilder;
    //   3631: ldc_w 377
    //   3634: invokevirtual 118	java/lang/StringBuilder:append	(Ljava/lang/String;)Ljava/lang/StringBuilder;
    //   3637: aload 146
    //   3639: invokevirtual 113	java/lang/StringBuilder:append	(Ljava/lang/Object;)Ljava/lang/StringBuilder;
    //   3642: invokevirtual 125	java/lang/StringBuilder:toString	()Ljava/lang/String;
    //   3645: invokestatic 289	android/util/Log:v	(Ljava/lang/String;Ljava/lang/String;)I
    //   3648: pop
    //   3649: goto +2541 -> 6190
    //   3652: ldc 208
    //   3654: new 108	java/lang/StringBuilder
    //   3657: dup
    //   3658: invokespecial 109	java/lang/StringBuilder:<init>	()V
    //   3661: ldc_w 523
    //   3664: invokevirtual 118	java/lang/StringBuilder:append	(Ljava/lang/String;)Ljava/lang/StringBuilder;
    //   3667: aload_0
    //   3668: getfield 17	com/google/android/gm/downloadprovider/DownloadThread:mInfo	Lcom/google/android/gm/downloadprovider/DownloadInfo;
    //   3671: getfield 91	com/google/android/gm/downloadprovider/DownloadInfo:mId	I
    //   3674: invokevirtual 121	java/lang/StringBuilder:append	(I)Ljava/lang/StringBuilder;
    //   3677: ldc_w 377
    //   3680: invokevirtual 118	java/lang/StringBuilder:append	(Ljava/lang/String;)Ljava/lang/StringBuilder;
    //   3683: aload 146
    //   3685: invokevirtual 113	java/lang/StringBuilder:append	(Ljava/lang/Object;)Ljava/lang/StringBuilder;
    //   3688: invokevirtual 125	java/lang/StringBuilder:toString	()Ljava/lang/String;
    //   3691: invokestatic 362	android/util/Log:d	(Ljava/lang/String;Ljava/lang/String;)I
    //   3694: pop
    //   3695: goto +2495 -> 6190
    //   3698: ldc 208
    //   3700: new 108	java/lang/StringBuilder
    //   3703: dup
    //   3704: invokespecial 109	java/lang/StringBuilder:<init>	()V
    //   3707: ldc_w 525
    //   3710: invokevirtual 118	java/lang/StringBuilder:append	(Ljava/lang/String;)Ljava/lang/StringBuilder;
    //   3713: aload_0
    //   3714: getfield 17	com/google/android/gm/downloadprovider/DownloadThread:mInfo	Lcom/google/android/gm/downloadprovider/DownloadInfo;
    //   3717: getfield 91	com/google/android/gm/downloadprovider/DownloadInfo:mId	I
    //   3720: invokevirtual 121	java/lang/StringBuilder:append	(I)Ljava/lang/StringBuilder;
    //   3723: invokevirtual 125	java/lang/StringBuilder:toString	()Ljava/lang/String;
    //   3726: invokestatic 362	android/util/Log:d	(Ljava/lang/String;Ljava/lang/String;)I
    //   3729: pop
    //   3730: goto -536 -> 3194
    //   3733: aload_0
    //   3734: getfield 15	com/google/android/gm/downloadprovider/DownloadThread:mContext	Landroid/content/Context;
    //   3737: invokestatic 388	com/google/android/gm/downloadprovider/Helpers:isNetworkAvailable	(Landroid/content/Context;)Z
    //   3740: ifne +22 -> 3762
    //   3743: sipush 193
    //   3746: istore_1
    //   3747: iload_2
    //   3748: istore 13
    //   3750: iconst_0
    //   3751: istore 15
    //   3753: iconst_0
    //   3754: istore 14
    //   3756: aconst_null
    //   3757: astore 12
    //   3759: goto -3082 -> 677
    //   3762: aload_0
    //   3763: getfield 17	com/google/android/gm/downloadprovider/DownloadThread:mInfo	Lcom/google/android/gm/downloadprovider/DownloadInfo;
    //   3766: getfield 106	com/google/android/gm/downloadprovider/DownloadInfo:mNumFailed	I
    //   3769: iconst_5
    //   3770: if_icmpge +22 -> 3792
    //   3773: sipush 193
    //   3776: istore_1
    //   3777: iconst_1
    //   3778: istore 15
    //   3780: iload_2
    //   3781: istore 13
    //   3783: iconst_0
    //   3784: istore 14
    //   3786: aconst_null
    //   3787: astore 12
    //   3789: goto -3112 -> 677
    //   3792: getstatic 281	com/google/android/gm/downloadprovider/Constants:LOGV	Z
    //   3795: ifeq +38 -> 3833
    //   3798: ldc 208
    //   3800: new 108	java/lang/StringBuilder
    //   3803: dup
    //   3804: invokespecial 109	java/lang/StringBuilder:<init>	()V
    //   3807: ldc_w 527
    //   3810: invokevirtual 118	java/lang/StringBuilder:append	(Ljava/lang/String;)Ljava/lang/StringBuilder;
    //   3813: aload_0
    //   3814: getfield 17	com/google/android/gm/downloadprovider/DownloadThread:mInfo	Lcom/google/android/gm/downloadprovider/DownloadInfo;
    //   3817: getfield 275	com/google/android/gm/downloadprovider/DownloadInfo:mUri	Ljava/lang/String;
    //   3820: invokevirtual 118	java/lang/StringBuilder:append	(Ljava/lang/String;)Ljava/lang/StringBuilder;
    //   3823: invokevirtual 125	java/lang/StringBuilder:toString	()Ljava/lang/String;
    //   3826: invokestatic 289	android/util/Log:v	(Ljava/lang/String;Ljava/lang/String;)I
    //   3829: pop
    //   3830: goto +2412 -> 6242
    //   3833: ldc 208
    //   3835: new 108	java/lang/StringBuilder
    //   3838: dup
    //   3839: invokespecial 109	java/lang/StringBuilder:<init>	()V
    //   3842: ldc_w 529
    //   3845: invokevirtual 118	java/lang/StringBuilder:append	(Ljava/lang/String;)Ljava/lang/StringBuilder;
    //   3848: aload_0
    //   3849: getfield 17	com/google/android/gm/downloadprovider/DownloadThread:mInfo	Lcom/google/android/gm/downloadprovider/DownloadInfo;
    //   3852: getfield 91	com/google/android/gm/downloadprovider/DownloadInfo:mId	I
    //   3855: invokevirtual 121	java/lang/StringBuilder:append	(I)Ljava/lang/StringBuilder;
    //   3858: invokevirtual 125	java/lang/StringBuilder:toString	()Ljava/lang/String;
    //   3861: invokestatic 362	android/util/Log:d	(Ljava/lang/String;Ljava/lang/String;)I
    //   3864: pop
    //   3865: goto +2377 -> 6242
    //   3868: iconst_1
    //   3869: istore 11
    //   3871: aload 5
    //   3873: astore 158
    //   3875: aload 158
    //   3877: ifnonnull +2174 -> 6051
    //   3880: new 242	java/io/FileOutputStream
    //   3883: dup
    //   3884: aload_3
    //   3885: iconst_1
    //   3886: invokespecial 365	java/io/FileOutputStream:<init>	(Ljava/lang/String;Z)V
    //   3889: astore 5
    //   3891: aload 5
    //   3893: aload 57
    //   3895: iconst_0
    //   3896: iload 157
    //   3898: invokevirtual 533	java/io/FileOutputStream:write	([BII)V
    //   3901: aload_0
    //   3902: getfield 17	com/google/android/gm/downloadprovider/DownloadThread:mInfo	Lcom/google/android/gm/downloadprovider/DownloadInfo;
    //   3905: getfield 270	com/google/android/gm/downloadprovider/DownloadInfo:mDestination	I
    //   3908: istore 161
    //   3910: iload 161
    //   3912: ifne +11 -> 3923
    //   3915: aload 5
    //   3917: invokevirtual 243	java/io/FileOutputStream:close	()V
    //   3920: aconst_null
    //   3921: astore 5
    //   3923: iload 58
    //   3925: iload 157
    //   3927: iadd
    //   3928: istore 58
    //   3930: invokestatic 63	java/lang/System:currentTimeMillis	()J
    //   3933: lstore 162
    //   3935: iload 58
    //   3937: iload 79
    //   3939: isub
    //   3940: sipush 4096
    //   3943: if_icmple +62 -> 4005
    //   3946: lload 162
    //   3948: lload 80
    //   3950: lsub
    //   3951: ldc2_w 534
    //   3954: lcmp
    //   3955: ifle +50 -> 4005
    //   3958: new 33	android/content/ContentValues
    //   3961: dup
    //   3962: invokespecial 34	android/content/ContentValues:<init>	()V
    //   3965: astore 169
    //   3967: aload 169
    //   3969: ldc_w 511
    //   3972: iload 58
    //   3974: invokestatic 42	java/lang/Integer:valueOf	(I)Ljava/lang/Integer;
    //   3977: invokevirtual 46	android/content/ContentValues:put	(Ljava/lang/String;Ljava/lang/Integer;)V
    //   3980: aload_0
    //   3981: getfield 15	com/google/android/gm/downloadprovider/DownloadThread:mContext	Landroid/content/Context;
    //   3984: invokevirtual 81	android/content/Context:getContentResolver	()Landroid/content/ContentResolver;
    //   3987: aload 8
    //   3989: aload 169
    //   3991: aconst_null
    //   3992: aconst_null
    //   3993: invokevirtual 103	android/content/ContentResolver:update	(Landroid/net/Uri;Landroid/content/ContentValues;Ljava/lang/String;[Ljava/lang/String;)I
    //   3996: pop
    //   3997: iload 58
    //   3999: istore 79
    //   4001: lload 162
    //   4003: lstore 80
    //   4005: getstatic 329	com/google/android/gm/downloadprovider/Constants:LOGVV	Z
    //   4008: ifeq +46 -> 4054
    //   4011: ldc 208
    //   4013: new 108	java/lang/StringBuilder
    //   4016: dup
    //   4017: invokespecial 109	java/lang/StringBuilder:<init>	()V
    //   4020: ldc_w 537
    //   4023: invokevirtual 118	java/lang/StringBuilder:append	(Ljava/lang/String;)Ljava/lang/StringBuilder;
    //   4026: iload 58
    //   4028: invokevirtual 121	java/lang/StringBuilder:append	(I)Ljava/lang/StringBuilder;
    //   4031: ldc_w 422
    //   4034: invokevirtual 118	java/lang/StringBuilder:append	(Ljava/lang/String;)Ljava/lang/StringBuilder;
    //   4037: aload_0
    //   4038: getfield 17	com/google/android/gm/downloadprovider/DownloadThread:mInfo	Lcom/google/android/gm/downloadprovider/DownloadInfo;
    //   4041: getfield 275	com/google/android/gm/downloadprovider/DownloadInfo:mUri	Ljava/lang/String;
    //   4044: invokevirtual 118	java/lang/StringBuilder:append	(Ljava/lang/String;)Ljava/lang/StringBuilder;
    //   4047: invokevirtual 125	java/lang/StringBuilder:toString	()Ljava/lang/String;
    //   4050: invokestatic 289	android/util/Log:v	(Ljava/lang/String;Ljava/lang/String;)I
    //   4053: pop
    //   4054: aload_0
    //   4055: getfield 17	com/google/android/gm/downloadprovider/DownloadThread:mInfo	Lcom/google/android/gm/downloadprovider/DownloadInfo;
    //   4058: astore 164
    //   4060: aload 164
    //   4062: monitorenter
    //   4063: aload_0
    //   4064: getfield 17	com/google/android/gm/downloadprovider/DownloadThread:mInfo	Lcom/google/android/gm/downloadprovider/DownloadInfo;
    //   4067: getfield 540	com/google/android/gm/downloadprovider/DownloadInfo:mControl	I
    //   4070: iconst_1
    //   4071: if_icmpne +151 -> 4222
    //   4074: getstatic 281	com/google/android/gm/downloadprovider/Constants:LOGV	Z
    //   4077: ifeq +35 -> 4112
    //   4080: ldc 208
    //   4082: new 108	java/lang/StringBuilder
    //   4085: dup
    //   4086: invokespecial 109	java/lang/StringBuilder:<init>	()V
    //   4089: ldc_w 542
    //   4092: invokevirtual 118	java/lang/StringBuilder:append	(Ljava/lang/String;)Ljava/lang/StringBuilder;
    //   4095: aload_0
    //   4096: getfield 17	com/google/android/gm/downloadprovider/DownloadThread:mInfo	Lcom/google/android/gm/downloadprovider/DownloadInfo;
    //   4099: getfield 275	com/google/android/gm/downloadprovider/DownloadInfo:mUri	Ljava/lang/String;
    //   4102: invokevirtual 118	java/lang/StringBuilder:append	(Ljava/lang/String;)Ljava/lang/StringBuilder;
    //   4105: invokevirtual 125	java/lang/StringBuilder:toString	()Ljava/lang/String;
    //   4108: invokestatic 289	android/util/Log:v	(Ljava/lang/String;Ljava/lang/String;)I
    //   4111: pop
    //   4112: sipush 193
    //   4115: istore_1
    //   4116: aload 83
    //   4118: invokevirtual 351	org/apache/http/client/methods/HttpGet:abort	()V
    //   4121: aload 164
    //   4123: monitorexit
    //   4124: iload_2
    //   4125: istore 13
    //   4127: iconst_0
    //   4128: istore 15
    //   4130: iconst_0
    //   4131: istore 14
    //   4133: aconst_null
    //   4134: astore 12
    //   4136: goto -3459 -> 677
    //   4139: astore 171
    //   4141: getstatic 281	com/google/android/gm/downloadprovider/Constants:LOGV	Z
    //   4144: ifeq -221 -> 3923
    //   4147: ldc 208
    //   4149: new 108	java/lang/StringBuilder
    //   4152: dup
    //   4153: invokespecial 109	java/lang/StringBuilder:<init>	()V
    //   4156: ldc_w 544
    //   4159: invokevirtual 118	java/lang/StringBuilder:append	(Ljava/lang/String;)Ljava/lang/StringBuilder;
    //   4162: aload 171
    //   4164: invokevirtual 113	java/lang/StringBuilder:append	(Ljava/lang/Object;)Ljava/lang/StringBuilder;
    //   4167: invokevirtual 125	java/lang/StringBuilder:toString	()Ljava/lang/String;
    //   4170: invokestatic 289	android/util/Log:v	(Ljava/lang/String;Ljava/lang/String;)I
    //   4173: pop
    //   4174: goto -251 -> 3923
    //   4177: astore 159
    //   4179: aload_0
    //   4180: getfield 15	com/google/android/gm/downloadprovider/DownloadThread:mContext	Landroid/content/Context;
    //   4183: ldc2_w 545
    //   4186: invokestatic 550	com/google/android/gm/downloadprovider/Helpers:discardPurgeableFiles	(Landroid/content/Context;J)Z
    //   4189: istore 160
    //   4191: iload 160
    //   4193: ifne +22 -> 4215
    //   4196: sipush 492
    //   4199: istore_1
    //   4200: iload_2
    //   4201: istore 13
    //   4203: iconst_0
    //   4204: istore 15
    //   4206: iconst_0
    //   4207: istore 14
    //   4209: aconst_null
    //   4210: astore 12
    //   4212: goto -3535 -> 677
    //   4215: aload 5
    //   4217: astore 158
    //   4219: goto -344 -> 3875
    //   4222: aload 164
    //   4224: monitorexit
    //   4225: aload_0
    //   4226: getfield 17	com/google/android/gm/downloadprovider/DownloadThread:mInfo	Lcom/google/android/gm/downloadprovider/DownloadInfo;
    //   4229: getfield 551	com/google/android/gm/downloadprovider/DownloadInfo:mStatus	I
    //   4232: sipush 490
    //   4235: if_icmpne -1185 -> 3050
    //   4238: getstatic 281	com/google/android/gm/downloadprovider/Constants:LOGV	Z
    //   4241: ifeq +35 -> 4276
    //   4244: ldc 208
    //   4246: new 108	java/lang/StringBuilder
    //   4249: dup
    //   4250: invokespecial 109	java/lang/StringBuilder:<init>	()V
    //   4253: ldc_w 553
    //   4256: invokevirtual 118	java/lang/StringBuilder:append	(Ljava/lang/String;)Ljava/lang/StringBuilder;
    //   4259: aload_0
    //   4260: getfield 17	com/google/android/gm/downloadprovider/DownloadThread:mInfo	Lcom/google/android/gm/downloadprovider/DownloadInfo;
    //   4263: getfield 275	com/google/android/gm/downloadprovider/DownloadInfo:mUri	Ljava/lang/String;
    //   4266: invokevirtual 118	java/lang/StringBuilder:append	(Ljava/lang/String;)Ljava/lang/StringBuilder;
    //   4269: invokevirtual 125	java/lang/StringBuilder:toString	()Ljava/lang/String;
    //   4272: invokestatic 362	android/util/Log:d	(Ljava/lang/String;Ljava/lang/String;)I
    //   4275: pop
    //   4276: sipush 490
    //   4279: istore_1
    //   4280: iload_2
    //   4281: istore 13
    //   4283: iconst_0
    //   4284: istore 15
    //   4286: iconst_0
    //   4287: istore 14
    //   4289: aconst_null
    //   4290: astore 12
    //   4292: goto -3615 -> 677
    //   4295: astore 165
    //   4297: aload 164
    //   4299: monitorexit
    //   4300: aload 165
    //   4302: athrow
    //   4303: getstatic 281	com/google/android/gm/downloadprovider/Constants:LOGV	Z
    //   4306: ifeq +35 -> 4341
    //   4309: ldc 208
    //   4311: new 108	java/lang/StringBuilder
    //   4314: dup
    //   4315: invokespecial 109	java/lang/StringBuilder:<init>	()V
    //   4318: ldc_w 555
    //   4321: invokevirtual 118	java/lang/StringBuilder:append	(Ljava/lang/String;)Ljava/lang/StringBuilder;
    //   4324: aload_0
    //   4325: getfield 17	com/google/android/gm/downloadprovider/DownloadThread:mInfo	Lcom/google/android/gm/downloadprovider/DownloadInfo;
    //   4328: getfield 275	com/google/android/gm/downloadprovider/DownloadInfo:mUri	Ljava/lang/String;
    //   4331: invokevirtual 118	java/lang/StringBuilder:append	(Ljava/lang/String;)Ljava/lang/StringBuilder;
    //   4334: invokevirtual 125	java/lang/StringBuilder:toString	()Ljava/lang/String;
    //   4337: invokestatic 289	android/util/Log:v	(Ljava/lang/String;Ljava/lang/String;)I
    //   4340: pop
    //   4341: sipush 200
    //   4344: istore_1
    //   4345: iload_2
    //   4346: istore 13
    //   4348: iconst_0
    //   4349: istore 15
    //   4351: iconst_0
    //   4352: istore 14
    //   4354: aconst_null
    //   4355: astore 12
    //   4357: goto -3680 -> 677
    //   4360: ldc 208
    //   4362: new 108	java/lang/StringBuilder
    //   4365: dup
    //   4366: invokespecial 109	java/lang/StringBuilder:<init>	()V
    //   4369: ldc_w 557
    //   4372: invokevirtual 118	java/lang/StringBuilder:append	(Ljava/lang/String;)Ljava/lang/StringBuilder;
    //   4375: aload_0
    //   4376: getfield 17	com/google/android/gm/downloadprovider/DownloadThread:mInfo	Lcom/google/android/gm/downloadprovider/DownloadInfo;
    //   4379: getfield 91	com/google/android/gm/downloadprovider/DownloadInfo:mId	I
    //   4382: invokevirtual 121	java/lang/StringBuilder:append	(I)Ljava/lang/StringBuilder;
    //   4385: invokevirtual 125	java/lang/StringBuilder:toString	()Ljava/lang/String;
    //   4388: aload 28
    //   4390: invokestatic 384	android/util/Log:d	(Ljava/lang/String;Ljava/lang/String;Ljava/lang/Throwable;)I
    //   4393: pop
    //   4394: goto -3089 -> 1305
    //   4397: astore 29
    //   4399: aload 29
    //   4401: astore 10
    //   4403: goto -2845 -> 1558
    //   4406: astore 25
    //   4408: getstatic 281	com/google/android/gm/downloadprovider/Constants:LOGV	Z
    //   4411: ifeq -2815 -> 1596
    //   4414: ldc 208
    //   4416: new 108	java/lang/StringBuilder
    //   4419: dup
    //   4420: invokespecial 109	java/lang/StringBuilder:<init>	()V
    //   4423: ldc_w 559
    //   4426: invokevirtual 118	java/lang/StringBuilder:append	(Ljava/lang/String;)Ljava/lang/StringBuilder;
    //   4429: aload 25
    //   4431: invokevirtual 113	java/lang/StringBuilder:append	(Ljava/lang/Object;)Ljava/lang/StringBuilder;
    //   4434: invokevirtual 125	java/lang/StringBuilder:toString	()Ljava/lang/String;
    //   4437: invokestatic 289	android/util/Log:v	(Ljava/lang/String;Ljava/lang/String;)I
    //   4440: pop
    //   4441: goto -2845 -> 1596
    //   4444: iload_1
    //   4445: invokestatic 562	com/google/android/gm/downloadprovider/Downloads$Impl:isStatusSuccess	(I)Z
    //   4448: ifeq -2827 -> 1621
    //   4451: new 242	java/io/FileOutputStream
    //   4454: dup
    //   4455: aload_3
    //   4456: iconst_1
    //   4457: invokespecial 365	java/io/FileOutputStream:<init>	(Ljava/lang/String;Z)V
    //   4460: invokevirtual 566	java/io/FileOutputStream:getFD	()Ljava/io/FileDescriptor;
    //   4463: invokevirtual 571	java/io/FileDescriptor:sync	()V
    //   4466: goto -2845 -> 1621
    //   4469: astore 22
    //   4471: ldc 208
    //   4473: new 108	java/lang/StringBuilder
    //   4476: dup
    //   4477: invokespecial 109	java/lang/StringBuilder:<init>	()V
    //   4480: ldc_w 573
    //   4483: invokevirtual 118	java/lang/StringBuilder:append	(Ljava/lang/String;)Ljava/lang/StringBuilder;
    //   4486: aload_3
    //   4487: invokevirtual 118	java/lang/StringBuilder:append	(Ljava/lang/String;)Ljava/lang/StringBuilder;
    //   4490: ldc_w 575
    //   4493: invokevirtual 118	java/lang/StringBuilder:append	(Ljava/lang/String;)Ljava/lang/StringBuilder;
    //   4496: aload 22
    //   4498: invokevirtual 113	java/lang/StringBuilder:append	(Ljava/lang/Object;)Ljava/lang/StringBuilder;
    //   4501: invokevirtual 125	java/lang/StringBuilder:toString	()Ljava/lang/String;
    //   4504: invokestatic 578	android/util/Log:w	(Ljava/lang/String;Ljava/lang/String;)I
    //   4507: pop
    //   4508: goto -2887 -> 1621
    //   4511: astore 20
    //   4513: ldc 208
    //   4515: new 108	java/lang/StringBuilder
    //   4518: dup
    //   4519: invokespecial 109	java/lang/StringBuilder:<init>	()V
    //   4522: ldc_w 573
    //   4525: invokevirtual 118	java/lang/StringBuilder:append	(Ljava/lang/String;)Ljava/lang/StringBuilder;
    //   4528: aload_3
    //   4529: invokevirtual 118	java/lang/StringBuilder:append	(Ljava/lang/String;)Ljava/lang/StringBuilder;
    //   4532: ldc_w 580
    //   4535: invokevirtual 118	java/lang/StringBuilder:append	(Ljava/lang/String;)Ljava/lang/StringBuilder;
    //   4538: aload 20
    //   4540: invokevirtual 113	java/lang/StringBuilder:append	(Ljava/lang/Object;)Ljava/lang/StringBuilder;
    //   4543: invokevirtual 125	java/lang/StringBuilder:toString	()Ljava/lang/String;
    //   4546: invokestatic 578	android/util/Log:w	(Ljava/lang/String;Ljava/lang/String;)I
    //   4549: pop
    //   4550: goto -2929 -> 1621
    //   4553: astore 18
    //   4555: ldc 208
    //   4557: new 108	java/lang/StringBuilder
    //   4560: dup
    //   4561: invokespecial 109	java/lang/StringBuilder:<init>	()V
    //   4564: ldc_w 582
    //   4567: invokevirtual 118	java/lang/StringBuilder:append	(Ljava/lang/String;)Ljava/lang/StringBuilder;
    //   4570: aload_3
    //   4571: invokevirtual 118	java/lang/StringBuilder:append	(Ljava/lang/String;)Ljava/lang/StringBuilder;
    //   4574: ldc_w 584
    //   4577: invokevirtual 118	java/lang/StringBuilder:append	(Ljava/lang/String;)Ljava/lang/StringBuilder;
    //   4580: aload 18
    //   4582: invokevirtual 113	java/lang/StringBuilder:append	(Ljava/lang/Object;)Ljava/lang/StringBuilder;
    //   4585: invokevirtual 125	java/lang/StringBuilder:toString	()Ljava/lang/String;
    //   4588: invokestatic 578	android/util/Log:w	(Ljava/lang/String;Ljava/lang/String;)I
    //   4591: pop
    //   4592: goto -2971 -> 1621
    //   4595: astore 16
    //   4597: ldc 208
    //   4599: ldc_w 586
    //   4602: aload 16
    //   4604: invokestatic 588	android/util/Log:w	(Ljava/lang/String;Ljava/lang/String;Ljava/lang/Throwable;)I
    //   4607: pop
    //   4608: goto -2987 -> 1621
    //   4611: astore 55
    //   4613: getstatic 281	com/google/android/gm/downloadprovider/Constants:LOGV	Z
    //   4616: ifeq -3524 -> 1092
    //   4619: ldc 208
    //   4621: new 108	java/lang/StringBuilder
    //   4624: dup
    //   4625: invokespecial 109	java/lang/StringBuilder:<init>	()V
    //   4628: ldc_w 559
    //   4631: invokevirtual 118	java/lang/StringBuilder:append	(Ljava/lang/String;)Ljava/lang/StringBuilder;
    //   4634: aload 55
    //   4636: invokevirtual 113	java/lang/StringBuilder:append	(Ljava/lang/Object;)Ljava/lang/StringBuilder;
    //   4639: invokevirtual 125	java/lang/StringBuilder:toString	()Ljava/lang/String;
    //   4642: invokestatic 289	android/util/Log:v	(Ljava/lang/String;Ljava/lang/String;)I
    //   4645: pop
    //   4646: goto -3554 -> 1092
    //   4649: iload_1
    //   4650: invokestatic 562	com/google/android/gm/downloadprovider/Downloads$Impl:isStatusSuccess	(I)Z
    //   4653: ifeq -3913 -> 740
    //   4656: new 242	java/io/FileOutputStream
    //   4659: dup
    //   4660: aload_3
    //   4661: iconst_1
    //   4662: invokespecial 365	java/io/FileOutputStream:<init>	(Ljava/lang/String;Z)V
    //   4665: invokevirtual 566	java/io/FileOutputStream:getFD	()Ljava/io/FileDescriptor;
    //   4668: invokevirtual 571	java/io/FileDescriptor:sync	()V
    //   4671: goto -3931 -> 740
    //   4674: astore 52
    //   4676: ldc 208
    //   4678: new 108	java/lang/StringBuilder
    //   4681: dup
    //   4682: invokespecial 109	java/lang/StringBuilder:<init>	()V
    //   4685: ldc_w 573
    //   4688: invokevirtual 118	java/lang/StringBuilder:append	(Ljava/lang/String;)Ljava/lang/StringBuilder;
    //   4691: aload_3
    //   4692: invokevirtual 118	java/lang/StringBuilder:append	(Ljava/lang/String;)Ljava/lang/StringBuilder;
    //   4695: ldc_w 575
    //   4698: invokevirtual 118	java/lang/StringBuilder:append	(Ljava/lang/String;)Ljava/lang/StringBuilder;
    //   4701: aload 52
    //   4703: invokevirtual 113	java/lang/StringBuilder:append	(Ljava/lang/Object;)Ljava/lang/StringBuilder;
    //   4706: invokevirtual 125	java/lang/StringBuilder:toString	()Ljava/lang/String;
    //   4709: invokestatic 578	android/util/Log:w	(Ljava/lang/String;Ljava/lang/String;)I
    //   4712: pop
    //   4713: goto -3973 -> 740
    //   4716: astore 50
    //   4718: ldc 208
    //   4720: new 108	java/lang/StringBuilder
    //   4723: dup
    //   4724: invokespecial 109	java/lang/StringBuilder:<init>	()V
    //   4727: ldc_w 573
    //   4730: invokevirtual 118	java/lang/StringBuilder:append	(Ljava/lang/String;)Ljava/lang/StringBuilder;
    //   4733: aload_3
    //   4734: invokevirtual 118	java/lang/StringBuilder:append	(Ljava/lang/String;)Ljava/lang/StringBuilder;
    //   4737: ldc_w 580
    //   4740: invokevirtual 118	java/lang/StringBuilder:append	(Ljava/lang/String;)Ljava/lang/StringBuilder;
    //   4743: aload 50
    //   4745: invokevirtual 113	java/lang/StringBuilder:append	(Ljava/lang/Object;)Ljava/lang/StringBuilder;
    //   4748: invokevirtual 125	java/lang/StringBuilder:toString	()Ljava/lang/String;
    //   4751: invokestatic 578	android/util/Log:w	(Ljava/lang/String;Ljava/lang/String;)I
    //   4754: pop
    //   4755: goto -4015 -> 740
    //   4758: astore 48
    //   4760: ldc 208
    //   4762: new 108	java/lang/StringBuilder
    //   4765: dup
    //   4766: invokespecial 109	java/lang/StringBuilder:<init>	()V
    //   4769: ldc_w 582
    //   4772: invokevirtual 118	java/lang/StringBuilder:append	(Ljava/lang/String;)Ljava/lang/StringBuilder;
    //   4775: aload_3
    //   4776: invokevirtual 118	java/lang/StringBuilder:append	(Ljava/lang/String;)Ljava/lang/StringBuilder;
    //   4779: ldc_w 584
    //   4782: invokevirtual 118	java/lang/StringBuilder:append	(Ljava/lang/String;)Ljava/lang/StringBuilder;
    //   4785: aload 48
    //   4787: invokevirtual 113	java/lang/StringBuilder:append	(Ljava/lang/Object;)Ljava/lang/StringBuilder;
    //   4790: invokevirtual 125	java/lang/StringBuilder:toString	()Ljava/lang/String;
    //   4793: invokestatic 578	android/util/Log:w	(Ljava/lang/String;Ljava/lang/String;)I
    //   4796: pop
    //   4797: goto -4057 -> 740
    //   4800: astore 46
    //   4802: ldc 208
    //   4804: ldc_w 586
    //   4807: aload 46
    //   4809: invokestatic 588	android/util/Log:w	(Ljava/lang/String;Ljava/lang/String;Ljava/lang/Throwable;)I
    //   4812: pop
    //   4813: goto -4073 -> 740
    //   4816: astore 40
    //   4818: getstatic 281	com/google/android/gm/downloadprovider/Constants:LOGV	Z
    //   4821: ifeq -3474 -> 1347
    //   4824: ldc 208
    //   4826: new 108	java/lang/StringBuilder
    //   4829: dup
    //   4830: invokespecial 109	java/lang/StringBuilder:<init>	()V
    //   4833: ldc_w 559
    //   4836: invokevirtual 118	java/lang/StringBuilder:append	(Ljava/lang/String;)Ljava/lang/StringBuilder;
    //   4839: aload 40
    //   4841: invokevirtual 113	java/lang/StringBuilder:append	(Ljava/lang/Object;)Ljava/lang/StringBuilder;
    //   4844: invokevirtual 125	java/lang/StringBuilder:toString	()Ljava/lang/String;
    //   4847: invokestatic 289	android/util/Log:v	(Ljava/lang/String;Ljava/lang/String;)I
    //   4850: pop
    //   4851: goto -3504 -> 1347
    //   4854: iload_1
    //   4855: invokestatic 562	com/google/android/gm/downloadprovider/Downloads$Impl:isStatusSuccess	(I)Z
    //   4858: ifeq -4118 -> 740
    //   4861: new 242	java/io/FileOutputStream
    //   4864: dup
    //   4865: aload_3
    //   4866: iconst_1
    //   4867: invokespecial 365	java/io/FileOutputStream:<init>	(Ljava/lang/String;Z)V
    //   4870: invokevirtual 566	java/io/FileOutputStream:getFD	()Ljava/io/FileDescriptor;
    //   4873: invokevirtual 571	java/io/FileDescriptor:sync	()V
    //   4876: goto -4136 -> 740
    //   4879: astore 37
    //   4881: ldc 208
    //   4883: new 108	java/lang/StringBuilder
    //   4886: dup
    //   4887: invokespecial 109	java/lang/StringBuilder:<init>	()V
    //   4890: ldc_w 573
    //   4893: invokevirtual 118	java/lang/StringBuilder:append	(Ljava/lang/String;)Ljava/lang/StringBuilder;
    //   4896: aload_3
    //   4897: invokevirtual 118	java/lang/StringBuilder:append	(Ljava/lang/String;)Ljava/lang/StringBuilder;
    //   4900: ldc_w 575
    //   4903: invokevirtual 118	java/lang/StringBuilder:append	(Ljava/lang/String;)Ljava/lang/StringBuilder;
    //   4906: aload 37
    //   4908: invokevirtual 113	java/lang/StringBuilder:append	(Ljava/lang/Object;)Ljava/lang/StringBuilder;
    //   4911: invokevirtual 125	java/lang/StringBuilder:toString	()Ljava/lang/String;
    //   4914: invokestatic 578	android/util/Log:w	(Ljava/lang/String;Ljava/lang/String;)I
    //   4917: pop
    //   4918: goto -4178 -> 740
    //   4921: astore 35
    //   4923: ldc 208
    //   4925: new 108	java/lang/StringBuilder
    //   4928: dup
    //   4929: invokespecial 109	java/lang/StringBuilder:<init>	()V
    //   4932: ldc_w 573
    //   4935: invokevirtual 118	java/lang/StringBuilder:append	(Ljava/lang/String;)Ljava/lang/StringBuilder;
    //   4938: aload_3
    //   4939: invokevirtual 118	java/lang/StringBuilder:append	(Ljava/lang/String;)Ljava/lang/StringBuilder;
    //   4942: ldc_w 580
    //   4945: invokevirtual 118	java/lang/StringBuilder:append	(Ljava/lang/String;)Ljava/lang/StringBuilder;
    //   4948: aload 35
    //   4950: invokevirtual 113	java/lang/StringBuilder:append	(Ljava/lang/Object;)Ljava/lang/StringBuilder;
    //   4953: invokevirtual 125	java/lang/StringBuilder:toString	()Ljava/lang/String;
    //   4956: invokestatic 578	android/util/Log:w	(Ljava/lang/String;Ljava/lang/String;)I
    //   4959: pop
    //   4960: goto -4220 -> 740
    //   4963: astore 33
    //   4965: ldc 208
    //   4967: new 108	java/lang/StringBuilder
    //   4970: dup
    //   4971: invokespecial 109	java/lang/StringBuilder:<init>	()V
    //   4974: ldc_w 582
    //   4977: invokevirtual 118	java/lang/StringBuilder:append	(Ljava/lang/String;)Ljava/lang/StringBuilder;
    //   4980: aload_3
    //   4981: invokevirtual 118	java/lang/StringBuilder:append	(Ljava/lang/String;)Ljava/lang/StringBuilder;
    //   4984: ldc_w 584
    //   4987: invokevirtual 118	java/lang/StringBuilder:append	(Ljava/lang/String;)Ljava/lang/StringBuilder;
    //   4990: aload 33
    //   4992: invokevirtual 113	java/lang/StringBuilder:append	(Ljava/lang/Object;)Ljava/lang/StringBuilder;
    //   4995: invokevirtual 125	java/lang/StringBuilder:toString	()Ljava/lang/String;
    //   4998: invokestatic 578	android/util/Log:w	(Ljava/lang/String;Ljava/lang/String;)I
    //   5001: pop
    //   5002: goto -4262 -> 740
    //   5005: astore 31
    //   5007: ldc 208
    //   5009: ldc_w 586
    //   5012: aload 31
    //   5014: invokestatic 588	android/util/Log:w	(Ljava/lang/String;Ljava/lang/String;Ljava/lang/Throwable;)I
    //   5017: pop
    //   5018: goto -4278 -> 740
    //   5021: astore 71
    //   5023: getstatic 281	com/google/android/gm/downloadprovider/Constants:LOGV	Z
    //   5026: ifeq -4823 -> 203
    //   5029: ldc 208
    //   5031: new 108	java/lang/StringBuilder
    //   5034: dup
    //   5035: invokespecial 109	java/lang/StringBuilder:<init>	()V
    //   5038: ldc_w 559
    //   5041: invokevirtual 118	java/lang/StringBuilder:append	(Ljava/lang/String;)Ljava/lang/StringBuilder;
    //   5044: aload 71
    //   5046: invokevirtual 113	java/lang/StringBuilder:append	(Ljava/lang/Object;)Ljava/lang/StringBuilder;
    //   5049: invokevirtual 125	java/lang/StringBuilder:toString	()Ljava/lang/String;
    //   5052: invokestatic 289	android/util/Log:v	(Ljava/lang/String;Ljava/lang/String;)I
    //   5055: pop
    //   5056: goto -4853 -> 203
    //   5059: iload_1
    //   5060: invokestatic 562	com/google/android/gm/downloadprovider/Downloads$Impl:isStatusSuccess	(I)Z
    //   5063: ifeq -4835 -> 228
    //   5066: new 242	java/io/FileOutputStream
    //   5069: dup
    //   5070: aload_3
    //   5071: iconst_1
    //   5072: invokespecial 365	java/io/FileOutputStream:<init>	(Ljava/lang/String;Z)V
    //   5075: invokevirtual 566	java/io/FileOutputStream:getFD	()Ljava/io/FileDescriptor;
    //   5078: invokevirtual 571	java/io/FileDescriptor:sync	()V
    //   5081: goto -4853 -> 228
    //   5084: astore 68
    //   5086: ldc 208
    //   5088: new 108	java/lang/StringBuilder
    //   5091: dup
    //   5092: invokespecial 109	java/lang/StringBuilder:<init>	()V
    //   5095: ldc_w 573
    //   5098: invokevirtual 118	java/lang/StringBuilder:append	(Ljava/lang/String;)Ljava/lang/StringBuilder;
    //   5101: aload_3
    //   5102: invokevirtual 118	java/lang/StringBuilder:append	(Ljava/lang/String;)Ljava/lang/StringBuilder;
    //   5105: ldc_w 575
    //   5108: invokevirtual 118	java/lang/StringBuilder:append	(Ljava/lang/String;)Ljava/lang/StringBuilder;
    //   5111: aload 68
    //   5113: invokevirtual 113	java/lang/StringBuilder:append	(Ljava/lang/Object;)Ljava/lang/StringBuilder;
    //   5116: invokevirtual 125	java/lang/StringBuilder:toString	()Ljava/lang/String;
    //   5119: invokestatic 578	android/util/Log:w	(Ljava/lang/String;Ljava/lang/String;)I
    //   5122: pop
    //   5123: goto -4895 -> 228
    //   5126: astore 66
    //   5128: ldc 208
    //   5130: new 108	java/lang/StringBuilder
    //   5133: dup
    //   5134: invokespecial 109	java/lang/StringBuilder:<init>	()V
    //   5137: ldc_w 573
    //   5140: invokevirtual 118	java/lang/StringBuilder:append	(Ljava/lang/String;)Ljava/lang/StringBuilder;
    //   5143: aload_3
    //   5144: invokevirtual 118	java/lang/StringBuilder:append	(Ljava/lang/String;)Ljava/lang/StringBuilder;
    //   5147: ldc_w 580
    //   5150: invokevirtual 118	java/lang/StringBuilder:append	(Ljava/lang/String;)Ljava/lang/StringBuilder;
    //   5153: aload 66
    //   5155: invokevirtual 113	java/lang/StringBuilder:append	(Ljava/lang/Object;)Ljava/lang/StringBuilder;
    //   5158: invokevirtual 125	java/lang/StringBuilder:toString	()Ljava/lang/String;
    //   5161: invokestatic 578	android/util/Log:w	(Ljava/lang/String;Ljava/lang/String;)I
    //   5164: pop
    //   5165: goto -4937 -> 228
    //   5168: astore 64
    //   5170: ldc 208
    //   5172: new 108	java/lang/StringBuilder
    //   5175: dup
    //   5176: invokespecial 109	java/lang/StringBuilder:<init>	()V
    //   5179: ldc_w 582
    //   5182: invokevirtual 118	java/lang/StringBuilder:append	(Ljava/lang/String;)Ljava/lang/StringBuilder;
    //   5185: aload_3
    //   5186: invokevirtual 118	java/lang/StringBuilder:append	(Ljava/lang/String;)Ljava/lang/StringBuilder;
    //   5189: ldc_w 584
    //   5192: invokevirtual 118	java/lang/StringBuilder:append	(Ljava/lang/String;)Ljava/lang/StringBuilder;
    //   5195: aload 64
    //   5197: invokevirtual 113	java/lang/StringBuilder:append	(Ljava/lang/Object;)Ljava/lang/StringBuilder;
    //   5200: invokevirtual 125	java/lang/StringBuilder:toString	()Ljava/lang/String;
    //   5203: invokestatic 578	android/util/Log:w	(Ljava/lang/String;Ljava/lang/String;)I
    //   5206: pop
    //   5207: goto -4979 -> 228
    //   5210: astore 62
    //   5212: ldc 208
    //   5214: ldc_w 586
    //   5217: aload 62
    //   5219: invokestatic 588	android/util/Log:w	(Ljava/lang/String;Ljava/lang/String;Ljava/lang/Throwable;)I
    //   5222: pop
    //   5223: goto -4995 -> 228
    //   5226: astore 98
    //   5228: getstatic 281	com/google/android/gm/downloadprovider/Constants:LOGV	Z
    //   5231: ifeq -4516 -> 715
    //   5234: ldc 208
    //   5236: new 108	java/lang/StringBuilder
    //   5239: dup
    //   5240: invokespecial 109	java/lang/StringBuilder:<init>	()V
    //   5243: ldc_w 559
    //   5246: invokevirtual 118	java/lang/StringBuilder:append	(Ljava/lang/String;)Ljava/lang/StringBuilder;
    //   5249: aload 98
    //   5251: invokevirtual 113	java/lang/StringBuilder:append	(Ljava/lang/Object;)Ljava/lang/StringBuilder;
    //   5254: invokevirtual 125	java/lang/StringBuilder:toString	()Ljava/lang/String;
    //   5257: invokestatic 289	android/util/Log:v	(Ljava/lang/String;Ljava/lang/String;)I
    //   5260: pop
    //   5261: goto -4546 -> 715
    //   5264: iload_1
    //   5265: invokestatic 562	com/google/android/gm/downloadprovider/Downloads$Impl:isStatusSuccess	(I)Z
    //   5268: ifeq -4528 -> 740
    //   5271: new 242	java/io/FileOutputStream
    //   5274: dup
    //   5275: aload_3
    //   5276: iconst_1
    //   5277: invokespecial 365	java/io/FileOutputStream:<init>	(Ljava/lang/String;Z)V
    //   5280: invokevirtual 566	java/io/FileOutputStream:getFD	()Ljava/io/FileDescriptor;
    //   5283: invokevirtual 571	java/io/FileDescriptor:sync	()V
    //   5286: goto -4546 -> 740
    //   5289: astore 95
    //   5291: ldc 208
    //   5293: new 108	java/lang/StringBuilder
    //   5296: dup
    //   5297: invokespecial 109	java/lang/StringBuilder:<init>	()V
    //   5300: ldc_w 573
    //   5303: invokevirtual 118	java/lang/StringBuilder:append	(Ljava/lang/String;)Ljava/lang/StringBuilder;
    //   5306: aload_3
    //   5307: invokevirtual 118	java/lang/StringBuilder:append	(Ljava/lang/String;)Ljava/lang/StringBuilder;
    //   5310: ldc_w 575
    //   5313: invokevirtual 118	java/lang/StringBuilder:append	(Ljava/lang/String;)Ljava/lang/StringBuilder;
    //   5316: aload 95
    //   5318: invokevirtual 113	java/lang/StringBuilder:append	(Ljava/lang/Object;)Ljava/lang/StringBuilder;
    //   5321: invokevirtual 125	java/lang/StringBuilder:toString	()Ljava/lang/String;
    //   5324: invokestatic 578	android/util/Log:w	(Ljava/lang/String;Ljava/lang/String;)I
    //   5327: pop
    //   5328: goto -4588 -> 740
    //   5331: astore 93
    //   5333: ldc 208
    //   5335: new 108	java/lang/StringBuilder
    //   5338: dup
    //   5339: invokespecial 109	java/lang/StringBuilder:<init>	()V
    //   5342: ldc_w 573
    //   5345: invokevirtual 118	java/lang/StringBuilder:append	(Ljava/lang/String;)Ljava/lang/StringBuilder;
    //   5348: aload_3
    //   5349: invokevirtual 118	java/lang/StringBuilder:append	(Ljava/lang/String;)Ljava/lang/StringBuilder;
    //   5352: ldc_w 580
    //   5355: invokevirtual 118	java/lang/StringBuilder:append	(Ljava/lang/String;)Ljava/lang/StringBuilder;
    //   5358: aload 93
    //   5360: invokevirtual 113	java/lang/StringBuilder:append	(Ljava/lang/Object;)Ljava/lang/StringBuilder;
    //   5363: invokevirtual 125	java/lang/StringBuilder:toString	()Ljava/lang/String;
    //   5366: invokestatic 578	android/util/Log:w	(Ljava/lang/String;Ljava/lang/String;)I
    //   5369: pop
    //   5370: goto -4630 -> 740
    //   5373: astore 91
    //   5375: ldc 208
    //   5377: new 108	java/lang/StringBuilder
    //   5380: dup
    //   5381: invokespecial 109	java/lang/StringBuilder:<init>	()V
    //   5384: ldc_w 582
    //   5387: invokevirtual 118	java/lang/StringBuilder:append	(Ljava/lang/String;)Ljava/lang/StringBuilder;
    //   5390: aload_3
    //   5391: invokevirtual 118	java/lang/StringBuilder:append	(Ljava/lang/String;)Ljava/lang/StringBuilder;
    //   5394: ldc_w 584
    //   5397: invokevirtual 118	java/lang/StringBuilder:append	(Ljava/lang/String;)Ljava/lang/StringBuilder;
    //   5400: aload 91
    //   5402: invokevirtual 113	java/lang/StringBuilder:append	(Ljava/lang/Object;)Ljava/lang/StringBuilder;
    //   5405: invokevirtual 125	java/lang/StringBuilder:toString	()Ljava/lang/String;
    //   5408: invokestatic 578	android/util/Log:w	(Ljava/lang/String;Ljava/lang/String;)I
    //   5411: pop
    //   5412: goto -4672 -> 740
    //   5415: astore 89
    //   5417: ldc 208
    //   5419: ldc_w 586
    //   5422: aload 89
    //   5424: invokestatic 588	android/util/Log:w	(Ljava/lang/String;Ljava/lang/String;Ljava/lang/Throwable;)I
    //   5427: pop
    //   5428: goto -4688 -> 740
    //   5431: astore 228
    //   5433: getstatic 281	com/google/android/gm/downloadprovider/Constants:LOGV	Z
    //   5436: ifeq -4586 -> 850
    //   5439: ldc 208
    //   5441: new 108	java/lang/StringBuilder
    //   5444: dup
    //   5445: invokespecial 109	java/lang/StringBuilder:<init>	()V
    //   5448: ldc_w 559
    //   5451: invokevirtual 118	java/lang/StringBuilder:append	(Ljava/lang/String;)Ljava/lang/StringBuilder;
    //   5454: aload 228
    //   5456: invokevirtual 113	java/lang/StringBuilder:append	(Ljava/lang/Object;)Ljava/lang/StringBuilder;
    //   5459: invokevirtual 125	java/lang/StringBuilder:toString	()Ljava/lang/String;
    //   5462: invokestatic 289	android/util/Log:v	(Ljava/lang/String;Ljava/lang/String;)I
    //   5465: pop
    //   5466: goto -4616 -> 850
    //   5469: iload_1
    //   5470: invokestatic 562	com/google/android/gm/downloadprovider/Downloads$Impl:isStatusSuccess	(I)Z
    //   5473: ifeq -4598 -> 875
    //   5476: new 242	java/io/FileOutputStream
    //   5479: dup
    //   5480: aload_3
    //   5481: iconst_1
    //   5482: invokespecial 365	java/io/FileOutputStream:<init>	(Ljava/lang/String;Z)V
    //   5485: invokevirtual 566	java/io/FileOutputStream:getFD	()Ljava/io/FileDescriptor;
    //   5488: invokevirtual 571	java/io/FileDescriptor:sync	()V
    //   5491: goto -4616 -> 875
    //   5494: astore 225
    //   5496: ldc 208
    //   5498: new 108	java/lang/StringBuilder
    //   5501: dup
    //   5502: invokespecial 109	java/lang/StringBuilder:<init>	()V
    //   5505: ldc_w 573
    //   5508: invokevirtual 118	java/lang/StringBuilder:append	(Ljava/lang/String;)Ljava/lang/StringBuilder;
    //   5511: aload_3
    //   5512: invokevirtual 118	java/lang/StringBuilder:append	(Ljava/lang/String;)Ljava/lang/StringBuilder;
    //   5515: ldc_w 575
    //   5518: invokevirtual 118	java/lang/StringBuilder:append	(Ljava/lang/String;)Ljava/lang/StringBuilder;
    //   5521: aload 225
    //   5523: invokevirtual 113	java/lang/StringBuilder:append	(Ljava/lang/Object;)Ljava/lang/StringBuilder;
    //   5526: invokevirtual 125	java/lang/StringBuilder:toString	()Ljava/lang/String;
    //   5529: invokestatic 578	android/util/Log:w	(Ljava/lang/String;Ljava/lang/String;)I
    //   5532: pop
    //   5533: goto -4658 -> 875
    //   5536: astore 223
    //   5538: ldc 208
    //   5540: new 108	java/lang/StringBuilder
    //   5543: dup
    //   5544: invokespecial 109	java/lang/StringBuilder:<init>	()V
    //   5547: ldc_w 573
    //   5550: invokevirtual 118	java/lang/StringBuilder:append	(Ljava/lang/String;)Ljava/lang/StringBuilder;
    //   5553: aload_3
    //   5554: invokevirtual 118	java/lang/StringBuilder:append	(Ljava/lang/String;)Ljava/lang/StringBuilder;
    //   5557: ldc_w 580
    //   5560: invokevirtual 118	java/lang/StringBuilder:append	(Ljava/lang/String;)Ljava/lang/StringBuilder;
    //   5563: aload 223
    //   5565: invokevirtual 113	java/lang/StringBuilder:append	(Ljava/lang/Object;)Ljava/lang/StringBuilder;
    //   5568: invokevirtual 125	java/lang/StringBuilder:toString	()Ljava/lang/String;
    //   5571: invokestatic 578	android/util/Log:w	(Ljava/lang/String;Ljava/lang/String;)I
    //   5574: pop
    //   5575: goto -4700 -> 875
    //   5578: astore 221
    //   5580: ldc 208
    //   5582: new 108	java/lang/StringBuilder
    //   5585: dup
    //   5586: invokespecial 109	java/lang/StringBuilder:<init>	()V
    //   5589: ldc_w 582
    //   5592: invokevirtual 118	java/lang/StringBuilder:append	(Ljava/lang/String;)Ljava/lang/StringBuilder;
    //   5595: aload_3
    //   5596: invokevirtual 118	java/lang/StringBuilder:append	(Ljava/lang/String;)Ljava/lang/StringBuilder;
    //   5599: ldc_w 584
    //   5602: invokevirtual 118	java/lang/StringBuilder:append	(Ljava/lang/String;)Ljava/lang/StringBuilder;
    //   5605: aload 221
    //   5607: invokevirtual 113	java/lang/StringBuilder:append	(Ljava/lang/Object;)Ljava/lang/StringBuilder;
    //   5610: invokevirtual 125	java/lang/StringBuilder:toString	()Ljava/lang/String;
    //   5613: invokestatic 578	android/util/Log:w	(Ljava/lang/String;Ljava/lang/String;)I
    //   5616: pop
    //   5617: goto -4742 -> 875
    //   5620: astore 219
    //   5622: ldc 208
    //   5624: ldc_w 586
    //   5627: aload 219
    //   5629: invokestatic 588	android/util/Log:w	(Ljava/lang/String;Ljava/lang/String;Ljava/lang/Throwable;)I
    //   5632: pop
    //   5633: goto -4758 -> 875
    //   5636: astore 215
    //   5638: aload 215
    //   5640: astore 10
    //   5642: aload 212
    //   5644: astore 5
    //   5646: iload_2
    //   5647: istore 13
    //   5649: iconst_0
    //   5650: istore 15
    //   5652: iconst_0
    //   5653: istore 14
    //   5655: iconst_0
    //   5656: istore 11
    //   5658: aconst_null
    //   5659: astore 12
    //   5661: aconst_null
    //   5662: astore 6
    //   5664: goto -4106 -> 1558
    //   5667: astore 88
    //   5669: aload 88
    //   5671: astore 10
    //   5673: iload_2
    //   5674: istore 13
    //   5676: iconst_0
    //   5677: istore 14
    //   5679: iconst_0
    //   5680: istore 11
    //   5682: aconst_null
    //   5683: astore 12
    //   5685: goto -4127 -> 1558
    //   5688: astore 202
    //   5690: aload 202
    //   5692: astore 10
    //   5694: iload_2
    //   5695: istore 13
    //   5697: iconst_0
    //   5698: istore 11
    //   5700: aconst_null
    //   5701: astore 12
    //   5703: goto -4145 -> 1558
    //   5706: astore 116
    //   5708: aload 116
    //   5710: astore 10
    //   5712: iconst_0
    //   5713: istore 15
    //   5715: iconst_0
    //   5716: istore 14
    //   5718: iconst_0
    //   5719: istore 11
    //   5721: goto -4163 -> 1558
    //   5724: astore 153
    //   5726: aload 153
    //   5728: astore 10
    //   5730: iload_2
    //   5731: istore 13
    //   5733: iconst_0
    //   5734: istore 14
    //   5736: aconst_null
    //   5737: astore 12
    //   5739: goto -4181 -> 1558
    //   5742: astore 176
    //   5744: aload 176
    //   5746: astore 10
    //   5748: aload 158
    //   5750: astore 5
    //   5752: iload_2
    //   5753: istore 13
    //   5755: iconst_0
    //   5756: istore 15
    //   5758: iconst_0
    //   5759: istore 14
    //   5761: aconst_null
    //   5762: astore 12
    //   5764: goto -4206 -> 1558
    //   5767: astore 214
    //   5769: aload 214
    //   5771: astore 28
    //   5773: aload 212
    //   5775: astore 5
    //   5777: iload_2
    //   5778: istore 13
    //   5780: iconst_0
    //   5781: istore 15
    //   5783: iconst_0
    //   5784: istore 14
    //   5786: iconst_0
    //   5787: istore 11
    //   5789: aconst_null
    //   5790: astore 12
    //   5792: aconst_null
    //   5793: astore 6
    //   5795: goto -4530 -> 1265
    //   5798: astore 87
    //   5800: aload 87
    //   5802: astore 28
    //   5804: iload_2
    //   5805: istore 13
    //   5807: iconst_0
    //   5808: istore 14
    //   5810: iconst_0
    //   5811: istore 11
    //   5813: aconst_null
    //   5814: astore 12
    //   5816: goto -4551 -> 1265
    //   5819: astore 201
    //   5821: aload 201
    //   5823: astore 28
    //   5825: iload_2
    //   5826: istore 13
    //   5828: iconst_0
    //   5829: istore 11
    //   5831: aconst_null
    //   5832: astore 12
    //   5834: goto -4569 -> 1265
    //   5837: astore 115
    //   5839: aload 115
    //   5841: astore 28
    //   5843: iconst_0
    //   5844: istore 15
    //   5846: iconst_0
    //   5847: istore 14
    //   5849: iconst_0
    //   5850: istore 11
    //   5852: goto -4587 -> 1265
    //   5855: astore 152
    //   5857: aload 152
    //   5859: astore 28
    //   5861: iload_2
    //   5862: istore 13
    //   5864: iconst_0
    //   5865: istore 14
    //   5867: aconst_null
    //   5868: astore 12
    //   5870: goto -4605 -> 1265
    //   5873: astore 175
    //   5875: aload 175
    //   5877: astore 28
    //   5879: aload 158
    //   5881: astore 5
    //   5883: iload_2
    //   5884: istore 13
    //   5886: iconst_0
    //   5887: istore 15
    //   5889: iconst_0
    //   5890: istore 14
    //   5892: aconst_null
    //   5893: astore 12
    //   5895: goto -4630 -> 1265
    //   5898: astore 213
    //   5900: aload 213
    //   5902: astore 44
    //   5904: aload 212
    //   5906: astore 5
    //   5908: iload_2
    //   5909: istore 13
    //   5911: iconst_0
    //   5912: istore 15
    //   5914: iconst_0
    //   5915: istore 14
    //   5917: iconst_0
    //   5918: istore 11
    //   5920: aconst_null
    //   5921: astore 12
    //   5923: aconst_null
    //   5924: astore 6
    //   5926: goto -4913 -> 1013
    //   5929: astore 86
    //   5931: aload 86
    //   5933: astore 44
    //   5935: iload_2
    //   5936: istore 13
    //   5938: iconst_0
    //   5939: istore 14
    //   5941: iconst_0
    //   5942: istore 11
    //   5944: aconst_null
    //   5945: astore 12
    //   5947: goto -4934 -> 1013
    //   5950: astore 200
    //   5952: aload 200
    //   5954: astore 44
    //   5956: iload_2
    //   5957: istore 13
    //   5959: iconst_0
    //   5960: istore 11
    //   5962: aconst_null
    //   5963: astore 12
    //   5965: goto -4952 -> 1013
    //   5968: astore 114
    //   5970: aload 114
    //   5972: astore 44
    //   5974: iconst_0
    //   5975: istore 15
    //   5977: iconst_0
    //   5978: istore 14
    //   5980: iconst_0
    //   5981: istore 11
    //   5983: goto -4970 -> 1013
    //   5986: astore 151
    //   5988: aload 151
    //   5990: astore 44
    //   5992: iload_2
    //   5993: istore 13
    //   5995: iconst_0
    //   5996: istore 14
    //   5998: aconst_null
    //   5999: astore 12
    //   6001: goto -4988 -> 1013
    //   6004: astore 174
    //   6006: aload 174
    //   6008: astore 44
    //   6010: aload 158
    //   6012: astore 5
    //   6014: iload_2
    //   6015: istore 13
    //   6017: iconst_0
    //   6018: istore 15
    //   6020: iconst_0
    //   6021: istore 14
    //   6023: aconst_null
    //   6024: astore 12
    //   6026: goto -5013 -> 1013
    //   6029: astore 173
    //   6031: aload 158
    //   6033: astore 5
    //   6035: goto -1856 -> 4179
    //   6038: astore 203
    //   6040: iconst_0
    //   6041: istore 14
    //   6043: goto -5380 -> 663
    //   6046: astore 205
    //   6048: goto -5385 -> 663
    //   6051: aload 158
    //   6053: astore 5
    //   6055: goto -2164 -> 3891
    //   6058: iconst_0
    //   6059: istore 14
    //   6061: goto -5398 -> 663
    //   6064: sipush 495
    //   6067: istore_1
    //   6068: iconst_0
    //   6069: istore 15
    //   6071: goto -4673 -> 1398
    //   6074: iload 59
    //   6076: ifne +11 -> 6087
    //   6079: iload 106
    //   6081: sipush 200
    //   6084: if_icmpne -3966 -> 2118
    //   6087: iload 59
    //   6089: ifeq -3842 -> 2247
    //   6092: iload 106
    //   6094: sipush 206
    //   6097: if_icmpeq -3850 -> 2247
    //   6100: goto -3982 -> 2118
    //   6103: iload 106
    //   6105: sipush 300
    //   6108: if_icmplt +18 -> 6126
    //   6111: iload 106
    //   6113: sipush 400
    //   6116: if_icmpge +10 -> 6126
    //   6119: sipush 493
    //   6122: istore_1
    //   6123: goto -3945 -> 2178
    //   6126: iload 59
    //   6128: ifeq +18 -> 6146
    //   6131: iload 106
    //   6133: sipush 200
    //   6136: if_icmpne +10 -> 6146
    //   6139: sipush 412
    //   6142: istore_1
    //   6143: goto -3965 -> 2178
    //   6146: sipush 494
    //   6149: istore_1
    //   6150: goto -3972 -> 2178
    //   6153: iconst_0
    //   6154: istore 133
    //   6156: goto -3333 -> 2823
    //   6159: sipush 495
    //   6162: istore_1
    //   6163: iconst_0
    //   6164: istore 15
    //   6166: goto -2930 -> 3236
    //   6169: astore 145
    //   6171: aload 145
    //   6173: astore 44
    //   6175: iload_2
    //   6176: istore 13
    //   6178: iconst_0
    //   6179: istore 15
    //   6181: iconst_0
    //   6182: istore 14
    //   6184: aconst_null
    //   6185: astore 12
    //   6187: goto -5174 -> 1013
    //   6190: sipush 495
    //   6193: istore_1
    //   6194: iconst_0
    //   6195: istore 15
    //   6197: goto -2701 -> 3496
    //   6200: astore 144
    //   6202: aload 144
    //   6204: astore 28
    //   6206: iload_2
    //   6207: istore 13
    //   6209: iconst_0
    //   6210: istore 15
    //   6212: iconst_0
    //   6213: istore 14
    //   6215: aconst_null
    //   6216: astore 12
    //   6218: goto -4953 -> 1265
    //   6221: astore 143
    //   6223: aload 143
    //   6225: astore 10
    //   6227: iload_2
    //   6228: istore 13
    //   6230: iconst_0
    //   6231: istore 15
    //   6233: iconst_0
    //   6234: istore 14
    //   6236: aconst_null
    //   6237: astore 12
    //   6239: goto -4681 -> 1558
    //   6242: sipush 495
    //   6245: istore_1
    //   6246: iload_2
    //   6247: istore 13
    //   6249: iconst_0
    //   6250: istore 15
    //   6252: iconst_0
    //   6253: istore 14
    //   6255: aconst_null
    //   6256: astore 12
    //   6258: goto -5581 -> 677
    //
    // Exception table:
    //   from	to	target	type
    //   353	358	954	java/io/IOException
    //   77	117	992	java/io/FileNotFoundException
    //   136	147	992	java/io/FileNotFoundException
    //   151	169	992	java/io/FileNotFoundException
    //   242	259	992	java/io/FileNotFoundException
    //   282	289	992	java/io/FileNotFoundException
    //   306	312	992	java/io/FileNotFoundException
    //   321	334	992	java/io/FileNotFoundException
    //   339	348	992	java/io/FileNotFoundException
    //   353	358	992	java/io/FileNotFoundException
    //   361	415	992	java/io/FileNotFoundException
    //   415	440	992	java/io/FileNotFoundException
    //   440	465	992	java/io/FileNotFoundException
    //   475	485	992	java/io/FileNotFoundException
    //   485	520	992	java/io/FileNotFoundException
    //   520	529	992	java/io/FileNotFoundException
    //   529	543	992	java/io/FileNotFoundException
    //   551	577	992	java/io/FileNotFoundException
    //   759	794	992	java/io/FileNotFoundException
    //   798	816	992	java/io/FileNotFoundException
    //   889	900	992	java/io/FileNotFoundException
    //   956	989	992	java/io/FileNotFoundException
    //   1122	1171	992	java/io/FileNotFoundException
    //   1175	1180	992	java/io/FileNotFoundException
    //   1198	1241	992	java/io/FileNotFoundException
    //   1377	1386	992	java/io/FileNotFoundException
    //   1418	1429	992	java/io/FileNotFoundException
    //   1439	1488	992	java/io/FileNotFoundException
    //   1491	1534	992	java/io/FileNotFoundException
    //   1725	1758	992	java/io/FileNotFoundException
    //   1763	1817	992	java/io/FileNotFoundException
    //   1821	1826	992	java/io/FileNotFoundException
    //   1844	1876	992	java/io/FileNotFoundException
    //   1879	1891	992	java/io/FileNotFoundException
    //   1896	1934	992	java/io/FileNotFoundException
    //   1934	1970	992	java/io/FileNotFoundException
    //   2002	2056	992	java/io/FileNotFoundException
    //   2060	2065	992	java/io/FileNotFoundException
    //   2083	2115	992	java/io/FileNotFoundException
    //   2118	2167	992	java/io/FileNotFoundException
    //   2167	2175	992	java/io/FileNotFoundException
    //   2178	2183	992	java/io/FileNotFoundException
    //   2201	2244	992	java/io/FileNotFoundException
    //   2247	2285	992	java/io/FileNotFoundException
    //   2290	2302	992	java/io/FileNotFoundException
    //   2310	2319	992	java/io/FileNotFoundException
    //   2319	2331	992	java/io/FileNotFoundException
    //   2339	2348	992	java/io/FileNotFoundException
    //   2348	2360	992	java/io/FileNotFoundException
    //   2368	2377	992	java/io/FileNotFoundException
    //   2382	2394	992	java/io/FileNotFoundException
    //   2399	2412	992	java/io/FileNotFoundException
    //   2412	2424	992	java/io/FileNotFoundException
    //   2429	2438	992	java/io/FileNotFoundException
    //   2438	2450	992	java/io/FileNotFoundException
    //   2458	2467	992	java/io/FileNotFoundException
    //   2472	2484	992	java/io/FileNotFoundException
    //   2489	2498	992	java/io/FileNotFoundException
    //   2498	2693	992	java/io/FileNotFoundException
    //   2693	2703	992	java/io/FileNotFoundException
    //   2713	2724	992	java/io/FileNotFoundException
    //   2724	2733	992	java/io/FileNotFoundException
    //   2737	2742	992	java/io/FileNotFoundException
    //   2760	2775	992	java/io/FileNotFoundException
    //   2778	2811	992	java/io/FileNotFoundException
    //   2816	2823	992	java/io/FileNotFoundException
    //   2823	2863	992	java/io/FileNotFoundException
    //   2881	2942	992	java/io/FileNotFoundException
    //   2942	2959	992	java/io/FileNotFoundException
    //   2964	2974	992	java/io/FileNotFoundException
    //   2979	2988	992	java/io/FileNotFoundException
    //   2996	3003	992	java/io/FileNotFoundException
    //   3003	3033	992	java/io/FileNotFoundException
    //   3033	3047	992	java/io/FileNotFoundException
    //   3215	3224	992	java/io/FileNotFoundException
    //   3256	3267	992	java/io/FileNotFoundException
    //   3277	3326	992	java/io/FileNotFoundException
    //   3329	3372	992	java/io/FileNotFoundException
    //   520	529	1120	java/lang/IllegalArgumentException
    //   77	117	1244	java/lang/RuntimeException
    //   136	147	1244	java/lang/RuntimeException
    //   151	169	1244	java/lang/RuntimeException
    //   242	259	1244	java/lang/RuntimeException
    //   282	289	1244	java/lang/RuntimeException
    //   306	312	1244	java/lang/RuntimeException
    //   321	334	1244	java/lang/RuntimeException
    //   339	348	1244	java/lang/RuntimeException
    //   353	358	1244	java/lang/RuntimeException
    //   361	415	1244	java/lang/RuntimeException
    //   415	440	1244	java/lang/RuntimeException
    //   440	465	1244	java/lang/RuntimeException
    //   475	485	1244	java/lang/RuntimeException
    //   485	520	1244	java/lang/RuntimeException
    //   520	529	1244	java/lang/RuntimeException
    //   529	543	1244	java/lang/RuntimeException
    //   551	577	1244	java/lang/RuntimeException
    //   759	794	1244	java/lang/RuntimeException
    //   798	816	1244	java/lang/RuntimeException
    //   889	900	1244	java/lang/RuntimeException
    //   956	989	1244	java/lang/RuntimeException
    //   1122	1171	1244	java/lang/RuntimeException
    //   1175	1180	1244	java/lang/RuntimeException
    //   1198	1241	1244	java/lang/RuntimeException
    //   1377	1386	1244	java/lang/RuntimeException
    //   1418	1429	1244	java/lang/RuntimeException
    //   1439	1488	1244	java/lang/RuntimeException
    //   1491	1534	1244	java/lang/RuntimeException
    //   1725	1758	1244	java/lang/RuntimeException
    //   1763	1817	1244	java/lang/RuntimeException
    //   1821	1826	1244	java/lang/RuntimeException
    //   1844	1876	1244	java/lang/RuntimeException
    //   1879	1891	1244	java/lang/RuntimeException
    //   1896	1934	1244	java/lang/RuntimeException
    //   1934	1970	1244	java/lang/RuntimeException
    //   2002	2056	1244	java/lang/RuntimeException
    //   2060	2065	1244	java/lang/RuntimeException
    //   2083	2115	1244	java/lang/RuntimeException
    //   2118	2167	1244	java/lang/RuntimeException
    //   2167	2175	1244	java/lang/RuntimeException
    //   2178	2183	1244	java/lang/RuntimeException
    //   2201	2244	1244	java/lang/RuntimeException
    //   2247	2285	1244	java/lang/RuntimeException
    //   2290	2302	1244	java/lang/RuntimeException
    //   2310	2319	1244	java/lang/RuntimeException
    //   2319	2331	1244	java/lang/RuntimeException
    //   2339	2348	1244	java/lang/RuntimeException
    //   2348	2360	1244	java/lang/RuntimeException
    //   2368	2377	1244	java/lang/RuntimeException
    //   2382	2394	1244	java/lang/RuntimeException
    //   2399	2412	1244	java/lang/RuntimeException
    //   2412	2424	1244	java/lang/RuntimeException
    //   2429	2438	1244	java/lang/RuntimeException
    //   2438	2450	1244	java/lang/RuntimeException
    //   2458	2467	1244	java/lang/RuntimeException
    //   2472	2484	1244	java/lang/RuntimeException
    //   2489	2498	1244	java/lang/RuntimeException
    //   2498	2693	1244	java/lang/RuntimeException
    //   2693	2703	1244	java/lang/RuntimeException
    //   2713	2724	1244	java/lang/RuntimeException
    //   2724	2733	1244	java/lang/RuntimeException
    //   2737	2742	1244	java/lang/RuntimeException
    //   2760	2775	1244	java/lang/RuntimeException
    //   2778	2811	1244	java/lang/RuntimeException
    //   2816	2823	1244	java/lang/RuntimeException
    //   2823	2863	1244	java/lang/RuntimeException
    //   2881	2942	1244	java/lang/RuntimeException
    //   2942	2959	1244	java/lang/RuntimeException
    //   2964	2974	1244	java/lang/RuntimeException
    //   2979	2988	1244	java/lang/RuntimeException
    //   2996	3003	1244	java/lang/RuntimeException
    //   3003	3033	1244	java/lang/RuntimeException
    //   3033	3047	1244	java/lang/RuntimeException
    //   3215	3224	1244	java/lang/RuntimeException
    //   3256	3267	1244	java/lang/RuntimeException
    //   3277	3326	1244	java/lang/RuntimeException
    //   3329	3372	1244	java/lang/RuntimeException
    //   520	529	1375	java/io/IOException
    //   77	117	1537	finally
    //   136	147	1537	finally
    //   151	169	1537	finally
    //   242	259	1537	finally
    //   282	289	1537	finally
    //   306	312	1537	finally
    //   321	334	1537	finally
    //   339	348	1537	finally
    //   353	358	1537	finally
    //   361	415	1537	finally
    //   415	440	1537	finally
    //   440	465	1537	finally
    //   475	485	1537	finally
    //   485	520	1537	finally
    //   520	529	1537	finally
    //   529	543	1537	finally
    //   551	577	1537	finally
    //   759	794	1537	finally
    //   798	816	1537	finally
    //   889	900	1537	finally
    //   956	989	1537	finally
    //   1122	1171	1537	finally
    //   1175	1180	1537	finally
    //   1198	1241	1537	finally
    //   1377	1386	1537	finally
    //   1418	1429	1537	finally
    //   1439	1488	1537	finally
    //   1491	1534	1537	finally
    //   1725	1758	1537	finally
    //   1763	1817	1537	finally
    //   1821	1826	1537	finally
    //   1844	1876	1537	finally
    //   1879	1891	1537	finally
    //   1896	1934	1537	finally
    //   1934	1970	1537	finally
    //   2002	2056	1537	finally
    //   2060	2065	1537	finally
    //   2083	2115	1537	finally
    //   2118	2167	1537	finally
    //   2167	2175	1537	finally
    //   2178	2183	1537	finally
    //   2201	2244	1537	finally
    //   2247	2285	1537	finally
    //   2290	2302	1537	finally
    //   2310	2319	1537	finally
    //   2319	2331	1537	finally
    //   2339	2348	1537	finally
    //   2348	2360	1537	finally
    //   2368	2377	1537	finally
    //   2382	2394	1537	finally
    //   2399	2412	1537	finally
    //   2412	2424	1537	finally
    //   2429	2438	1537	finally
    //   2438	2450	1537	finally
    //   2458	2467	1537	finally
    //   2472	2484	1537	finally
    //   2489	2498	1537	finally
    //   2498	2693	1537	finally
    //   2693	2703	1537	finally
    //   2713	2724	1537	finally
    //   2724	2733	1537	finally
    //   2737	2742	1537	finally
    //   2760	2775	1537	finally
    //   2778	2811	1537	finally
    //   2816	2823	1537	finally
    //   2823	2863	1537	finally
    //   2881	2942	1537	finally
    //   2942	2959	1537	finally
    //   2964	2974	1537	finally
    //   2979	2988	1537	finally
    //   2996	3003	1537	finally
    //   3003	3033	1537	finally
    //   3033	3047	1537	finally
    //   3215	3224	1537	finally
    //   3256	3267	1537	finally
    //   3277	3326	1537	finally
    //   3329	3372	1537	finally
    //   1934	1970	2000	java/net/URISyntaxException
    //   3033	3047	3213	java/io/IOException
    //   3050	3059	3375	java/io/IOException
    //   3915	3920	4139	java/io/IOException
    //   3891	3910	4177	java/io/IOException
    //   4141	4174	4177	java/io/IOException
    //   4063	4112	4295	finally
    //   4116	4124	4295	finally
    //   4222	4225	4295	finally
    //   4297	4300	4295	finally
    //   1013	1050	4397	finally
    //   1265	1305	4397	finally
    //   4360	4394	4397	finally
    //   1591	1596	4406	java/io/IOException
    //   4451	4466	4469	java/io/FileNotFoundException
    //   4451	4466	4511	java/io/SyncFailedException
    //   4451	4466	4553	java/io/IOException
    //   4451	4466	4595	java/lang/RuntimeException
    //   1087	1092	4611	java/io/IOException
    //   4656	4671	4674	java/io/FileNotFoundException
    //   4656	4671	4716	java/io/SyncFailedException
    //   4656	4671	4758	java/io/IOException
    //   4656	4671	4800	java/lang/RuntimeException
    //   1342	1347	4816	java/io/IOException
    //   4861	4876	4879	java/io/FileNotFoundException
    //   4861	4876	4921	java/io/SyncFailedException
    //   4861	4876	4963	java/io/IOException
    //   4861	4876	5005	java/lang/RuntimeException
    //   199	203	5021	java/io/IOException
    //   5066	5081	5084	java/io/FileNotFoundException
    //   5066	5081	5126	java/io/SyncFailedException
    //   5066	5081	5168	java/io/IOException
    //   5066	5081	5210	java/lang/RuntimeException
    //   710	715	5226	java/io/IOException
    //   5271	5286	5289	java/io/FileNotFoundException
    //   5271	5286	5331	java/io/SyncFailedException
    //   5271	5286	5373	java/io/IOException
    //   5271	5286	5415	java/lang/RuntimeException
    //   846	850	5431	java/io/IOException
    //   5476	5491	5494	java/io/FileNotFoundException
    //   5476	5491	5536	java/io/SyncFailedException
    //   5476	5491	5578	java/io/IOException
    //   5476	5491	5620	java/lang/RuntimeException
    //   905	914	5636	finally
    //   923	935	5636	finally
    //   935	944	5636	finally
    //   584	596	5667	finally
    //   601	639	5667	finally
    //   639	651	5667	finally
    //   1398	1403	5667	finally
    //   3236	3241	5667	finally
    //   663	668	5688	finally
    //   1653	1663	5688	finally
    //   1983	1988	5706	finally
    //   3496	3501	5724	finally
    //   3880	3891	5742	finally
    //   905	914	5767	java/lang/RuntimeException
    //   923	935	5767	java/lang/RuntimeException
    //   935	944	5767	java/lang/RuntimeException
    //   584	596	5798	java/lang/RuntimeException
    //   601	639	5798	java/lang/RuntimeException
    //   639	651	5798	java/lang/RuntimeException
    //   1398	1403	5798	java/lang/RuntimeException
    //   3236	3241	5798	java/lang/RuntimeException
    //   663	668	5819	java/lang/RuntimeException
    //   1653	1663	5819	java/lang/RuntimeException
    //   1983	1988	5837	java/lang/RuntimeException
    //   3496	3501	5855	java/lang/RuntimeException
    //   3880	3891	5873	java/lang/RuntimeException
    //   905	914	5898	java/io/FileNotFoundException
    //   923	935	5898	java/io/FileNotFoundException
    //   935	944	5898	java/io/FileNotFoundException
    //   584	596	5929	java/io/FileNotFoundException
    //   601	639	5929	java/io/FileNotFoundException
    //   639	651	5929	java/io/FileNotFoundException
    //   1398	1403	5929	java/io/FileNotFoundException
    //   3236	3241	5929	java/io/FileNotFoundException
    //   663	668	5950	java/io/FileNotFoundException
    //   1653	1663	5950	java/io/FileNotFoundException
    //   1983	1988	5968	java/io/FileNotFoundException
    //   3496	3501	5986	java/io/FileNotFoundException
    //   3880	3891	6004	java/io/FileNotFoundException
    //   3880	3891	6029	java/io/IOException
    //   601	639	6038	java/lang/NumberFormatException
    //   639	651	6038	java/lang/NumberFormatException
    //   1653	1663	6046	java/lang/NumberFormatException
    //   3050	3059	6169	java/io/FileNotFoundException
    //   3065	3087	6169	java/io/FileNotFoundException
    //   3092	3105	6169	java/io/FileNotFoundException
    //   3105	3122	6169	java/io/FileNotFoundException
    //   3127	3134	6169	java/io/FileNotFoundException
    //   3141	3151	6169	java/io/FileNotFoundException
    //   3156	3194	6169	java/io/FileNotFoundException
    //   3377	3426	6169	java/io/FileNotFoundException
    //   3431	3480	6169	java/io/FileNotFoundException
    //   3480	3489	6169	java/io/FileNotFoundException
    //   3513	3556	6169	java/io/FileNotFoundException
    //   3559	3569	6169	java/io/FileNotFoundException
    //   3579	3590	6169	java/io/FileNotFoundException
    //   3600	3649	6169	java/io/FileNotFoundException
    //   3652	3695	6169	java/io/FileNotFoundException
    //   3698	3730	6169	java/io/FileNotFoundException
    //   3733	3743	6169	java/io/FileNotFoundException
    //   3762	3773	6169	java/io/FileNotFoundException
    //   3792	3830	6169	java/io/FileNotFoundException
    //   3833	3865	6169	java/io/FileNotFoundException
    //   3891	3910	6169	java/io/FileNotFoundException
    //   3915	3920	6169	java/io/FileNotFoundException
    //   3930	3935	6169	java/io/FileNotFoundException
    //   3958	3997	6169	java/io/FileNotFoundException
    //   4005	4054	6169	java/io/FileNotFoundException
    //   4054	4063	6169	java/io/FileNotFoundException
    //   4141	4174	6169	java/io/FileNotFoundException
    //   4179	4191	6169	java/io/FileNotFoundException
    //   4225	4276	6169	java/io/FileNotFoundException
    //   4300	4303	6169	java/io/FileNotFoundException
    //   4303	4341	6169	java/io/FileNotFoundException
    //   3050	3059	6200	java/lang/RuntimeException
    //   3065	3087	6200	java/lang/RuntimeException
    //   3092	3105	6200	java/lang/RuntimeException
    //   3105	3122	6200	java/lang/RuntimeException
    //   3127	3134	6200	java/lang/RuntimeException
    //   3141	3151	6200	java/lang/RuntimeException
    //   3156	3194	6200	java/lang/RuntimeException
    //   3377	3426	6200	java/lang/RuntimeException
    //   3431	3480	6200	java/lang/RuntimeException
    //   3480	3489	6200	java/lang/RuntimeException
    //   3513	3556	6200	java/lang/RuntimeException
    //   3559	3569	6200	java/lang/RuntimeException
    //   3579	3590	6200	java/lang/RuntimeException
    //   3600	3649	6200	java/lang/RuntimeException
    //   3652	3695	6200	java/lang/RuntimeException
    //   3698	3730	6200	java/lang/RuntimeException
    //   3733	3743	6200	java/lang/RuntimeException
    //   3762	3773	6200	java/lang/RuntimeException
    //   3792	3830	6200	java/lang/RuntimeException
    //   3833	3865	6200	java/lang/RuntimeException
    //   3891	3910	6200	java/lang/RuntimeException
    //   3915	3920	6200	java/lang/RuntimeException
    //   3930	3935	6200	java/lang/RuntimeException
    //   3958	3997	6200	java/lang/RuntimeException
    //   4005	4054	6200	java/lang/RuntimeException
    //   4054	4063	6200	java/lang/RuntimeException
    //   4141	4174	6200	java/lang/RuntimeException
    //   4179	4191	6200	java/lang/RuntimeException
    //   4225	4276	6200	java/lang/RuntimeException
    //   4300	4303	6200	java/lang/RuntimeException
    //   4303	4341	6200	java/lang/RuntimeException
    //   3050	3059	6221	finally
    //   3065	3087	6221	finally
    //   3092	3105	6221	finally
    //   3105	3122	6221	finally
    //   3127	3134	6221	finally
    //   3141	3151	6221	finally
    //   3156	3194	6221	finally
    //   3377	3426	6221	finally
    //   3431	3480	6221	finally
    //   3480	3489	6221	finally
    //   3513	3556	6221	finally
    //   3559	3569	6221	finally
    //   3579	3590	6221	finally
    //   3600	3649	6221	finally
    //   3652	3695	6221	finally
    //   3698	3730	6221	finally
    //   3733	3743	6221	finally
    //   3762	3773	6221	finally
    //   3792	3830	6221	finally
    //   3833	3865	6221	finally
    //   3891	3910	6221	finally
    //   3915	3920	6221	finally
    //   3930	3935	6221	finally
    //   3958	3997	6221	finally
    //   4005	4054	6221	finally
    //   4054	4063	6221	finally
    //   4141	4174	6221	finally
    //   4179	4191	6221	finally
    //   4225	4276	6221	finally
    //   4300	4303	6221	finally
    //   4303	4341	6221	finally
  }
}

/* Location:           C:\Users\\Desktop\classes_dex2jar.jar
 * Qualified Name:     com.google.android.gm.downloadprovider.DownloadThread
 * JD-Core Version:    0.6.2
 */